Workbook

Sheet Assumptions
A1: COCA-COLA COMPANY — FINANCIAL MODEL ASSUMPTIONS
A2: All figures in USD Millions unless stated | Fiscal Year ends December 31
B4: 2019 | C4: 2020 | D4: 2021 | E4: 2022 | F4: 2023 | G4: 2024 | H4: 2025
B5: Historical | C5: Historical | D5: Historical | E5: Historical | F5: Historical | G5: Projected | H5: Projected
A6: REVENUE ASSUMPTIONS
A7: Net Revenue ($mm) | B7: 37266 | C7: 33014 | D7: 38655 | E7: 43004 | F7: 45754 | G7: =F7*(1+G9) -> 45754 | H7: =G7*(1+H9) -> 45754
A8: Revenue Growth YoY | B8: N/A | C8: =(C7-B7)/B7 -> -0.11409864 | D8: =(D7-C7)/C7 -> 0.1708669 | E8: =(E7-D7)/D7 -> 0.11250808 | F8: =(F7-E7)/E7 -> 0.06394754 | G8: 0.05 | H8: 0.05
A10: MARGIN ASSUMPTIONS
A11: Gross Profit Margin | B11: 0.601 | C11: 0.596 | D11: 0.604 | E11: 0.582 | F11: 0.592 | G11: 0.595 | H11: 0.6
A12: EBITDA Margin | B12: 0.265 | C12: 0.252 | D12: 0.288 | E12: 0.279 | F12: 0.288 | G12: 0.29 | H12: 0.292
A13: EBIT Margin (Operating Margin) | B13: 0.27 | C13: 0.212 | D13: 0.264 | E13: 0.254 | F13: 0.261 | G13: 0.265 | H13: 0.268
A14: Net Income Margin | B14: 0.234 | C14: 0.186 | D14: 0.252 | E14: 0.228 | F14: 0.239 | G14: 0.24 | H14: 0.242
A16: DCF ASSUMPTIONS
A17: WACC (Discount Rate) | B17: 0.082 | C17: ← Key Assumption
A18: Terminal Growth Rate | B18: 0.025 | C18: ← Key Assumption
A19: Tax Rate | B19: 0.187 | C19: ← Key Assumption
A20: D&A as % of Revenue | B20: 0.04 | C20: ← Key Assumption
A21: Capex as % of Revenue | B21: 0.045 | C21: ← Key Assumption
A22: Change in NWC as % of Revenue | B22: 0.01 | C22: ← Key Assumption
A25: Source: Coca-Cola Company 10-K Filings (2019–2023), SEC EDGAR. Projections based on analyst consensus and historical trend analysis.

Sheet Income Statement
A1: COCA-COLA COMPANY — INCOME STATEMENT
A2: USD Millions | Fiscal Year ends December 31
B4: 2019 | C4: 2020 | D4: 2021 | E4: 2022 | F4: 2023 | G4: 2024 | H4: 2025
B5: Historical | C5: Historical | D5: Historical | E5: Historical | F5: Historical | G5: Projected | H5: Projected
A6: INCOME STATEMENT ($mm)
A7: Net Revenue | B7: 37266 | C7: 33014 | D7: 38655 | E7: 43004 | F7: 45754 | G7: =Assumptions!G7 -> 45754 | H7: =Assumptions!H7 -> 45754
A8: Cost of Goods Sold | B8: =14880 -> 14880 | C8: =13433 -> 13433 | D8: =15357 -> 15357 | E8: =18001 -> 18001 | F8: =18670 -> 18670 | G8: =G7*(1-Assumptions!G11) -> 18530.37 | H8: =H7*(1-Assumptions!H11) -> 18301.6
A9: Gross Profit | B9: =B7-B8 -> 22386 | C9: =C7-C8 -> 19581 | D9: =D7-D8 -> 23298 | E9: =E7-E8 -> 25003 | F9: =F7-F8 -> 27084 | G9: =G7-G8 -> 27223.63 | H9: =H7-H8 -> 27452.4
A10: Gross Margin % | B10: =B9/B7 -> 0.60070842 | C10: =C9/C7 -> 0.59311201 | D10: =D9/D7 -> 0.60271634 | E10: =E9/E7 -> 0.58141103 | F10: =F9/F7 -> 0.59194824 | G10: =G9/G7 -> 0.595 | H10: =H9/H7 -> 0.6
A11: OPERATING EXPENSES
A12: Selling & Marketing Expenses | B12: 4050 | C12: 3890 | D12: 4165 | E12: 4600 | F12: 4810 | G12: =G7*0.1 -> 4575.4 | H12: =H7*0.1 -> 4575.4
A13: General & Administrative Expenses | B13: 1900 | C13: 1850 | D13: 2100 | E13: 2400 | F13: 2550 | G13: =G7*0.053 -> 2424.962 | H13: =H7*0.053 -> 2424.962
A14: D&A (Depreciation & Amortization) | B14: 1365 | C14: 1350 | D14: 1260 | E14: 1310 | F14: 1450 | G14: =G7*Assumptions!$B$20 -> 1830.16 | H14: =H7*Assumptions!$B$20 -> 1830.16
A15: Total Operating Expenses | B15: =SUM(B12:B14) -> 7315 | C15: =SUM(C12:C14) -> 7090 | D15: =SUM(D12:D14) -> 7525 | E15: =SUM(E12:E14) -> 8310 | F15: =SUM(F12:F14) -> 8810 | G15: =SUM(G12:G14) -> 8830.522 | H15: =SUM(H12:H14) -> 8830.522
A16: EBIT (Operating Income) | B16: =B9-B15 -> 15071 | C16: =C9-C15 -> 12491 | D16: =D9-D15 -> 15773 | E16: =E9-E15 -> 16693 | F16: =F9-F15 -> 18274 | G16: =G9-G15 -> 18393.108 | H16: =H9-H15 -> 18621.878
A17: EBIT Margin % | B17: =B16/B7 -> 0.40441689 | C17: =C16/C7 -> 0.37835464 | D17: =D16/D7 -> 0.40804553 | E17: =E16/E7 -> 0.38817319 | F17: =F16/F7 -> 0.39939677 | G17: =G16/G7 -> 0.402 | H17: =H16/H7 -> 0.407
A18: EBITDA | B18: =B16+B14 -> 16436 | C18: =C16+C14 -> 13841 | D18: =D16+D14 -> 17033 | E18: =E16+E14 -> 18003 | F18: =F16+F14 -> 19724 | G18: =G16+G14 -> 20223.268 | H18: =H16+H14 -> 20452.038
A19: EBITDA Margin % | B19: =B18/B7 -> 0.44104546 | C19: =C18/C7 -> 0.41924638 | D19: =D18/D7 -> 0.44064157 | E19: =E18/E7 -> 0.41863548 | F19: =F18/F7 -> 0.43108799 | G19: =G18/G7 -> 0.442 | H19: =H18/H7 -> 0.447
A20: BELOW THE LINE
A21: Interest Expense | B21: -946 | C21: -1183 | D21: -1597 | E21: -882 | F21: -879 | G21: -900 | H21: -900
A22: Other Income / (Expense) | B22: 673 | C22: 841 | D22: 1045 | E22: 1107 | F22: 1234 | G22: 1200 | H22: 1200
A23: Pre-Tax Income (EBT) | B23: =B16+B21+B22 -> 14798 | C23: =C16+C21+C22 -> 12149 | D23: =D16+D21+D22 -> 15221 | E23: =E16+E21+E22 -> 16918 | F23: =F16+F21+F22 -> 18629 | G23: =G16+G21+G22 -> 18693.108 | H23: =H16+H21+H22 -> 18921.878
A24: Income Tax Expense | B24: =-B23*Assumptions!$B$19 -> -2767.226 | C24: =-C23*Assumptions!$B$19 -> -2271.863 | D24: =-D23*Assumptions!$B$19 -> -2846.327 | E24: =-E23*Assumptions!$B$19 -> -3163.666 | F24: =-F23*Assumptions!$B$19 -> -3483.623 | G24: =-G23*Assumptions!$B$19 -> -3495.6112 | H24: =-H23*Assumptions!$B$19 -> -3538.3912
A25: Net Income | B25: =B23+B24 -> 12030.774 | C25: =C23+C24 -> 9877.137 | D25: =D23+D24 -> 12374.673 | E25: =E23+E24 -> 13754.334 | F25: =F23+F24 -> 15145.377 | G25: =G23+G24 -> 15197.497 | H25: =H23+H24 -> 15383.487
A26: Net Margin % | B26: =B25/B7 -> 0.32283513 | C26: =C25/C7 -> 0.29918026 | D26: =D25/D7 -> 0.32013124 | E26: =E25/E7 -> 0.31983848 | F26: =F25/F7 -> 0.33101755 | G26: =G25/G7 -> 0.33215668 | H26: =H25/H7 -> 0.33622168
A27: PER SHARE DATA
A28: Shares Outstanding (mm) | B28: 4295 | C28: 4280 | D28: 4315 | E28: 4328 | F28: 4326 | G28: 4320 | H28: 4310
A29: EPS (Basic) | B29: =B25/B28 -> 2.8011115 | C29: =C25/C28 -> 2.3077423 | D29: =D25/D28 -> 2.8678269 | E29: =E25/E28 -> 3.1779884 | F29: =F25/F28 -> 3.5010118 | G29: =G25/G28 -> 3.5179391 | H29: =H25/H28 -> 3.5692545
A30: Dividends Per Share | B30: 1.64 | C30: 1.68 | D30: 1.72 | E30: 1.76 | F30: 1.84 | G30: 1.94 | H30: 2.04

Sheet DCF Valuation
A1: COCA-COLA COMPANY — DCF VALUATION
A2: Discounted Cash Flow Analysis | USD Millions
A4: FREE CASH FLOW BUILD ($mm)
B5: 2024 | C5: 2025 | D5: 2026 | E5: 2027 | F5: 2028
A6: EBIT (Operating Income) | B6: 12725 | C6: 13520 | D6: 14196 | E6: 14906 | F6: 15651
A7: Tax on EBIT (NOPAT Tax) | B7: =-B6*Assumptions!$B$19 -> -2379.575 | C7: =-C6*Assumptions!$B$19 -> -2528.24 | D7: =-D6*Assumptions!$B$19 -> -2654.652 | E7: =-E6*Assumptions!$B$19 -> -2787.422 | F7: =-F6*Assumptions!$B$19 -> -2926.737
A8: NOPAT (Net Operating Profit After Tax) | B8: =B6+B7 -> 10345.425 | C8: =C6+C7 -> 10991.76 | D8: =D6+D7 -> 11541.348 | E8: =E6+E7 -> 12118.578 | F8: =F6+F7 -> 12724.263
A9: Add: D&A | B9: 1921 | C9: 2018 | D9: 2119 | E9: 2225 | F9: 2336
A10: Less: Capital Expenditures | B10: -2162 | C10: -2272 | D10: -2386 | E10: -2505 | F10: -2630
A11: Less: Change in Net Working Capital | B11: -481 | C11: -505 | D11: -530 | E11: -557 | F11: -585
A12: Unlevered Free Cash Flow (UFCF) | B12: =SUM(B8:B11) -> 9623.425 | C12: =SUM(C8:C11) -> 10232.76 | D12: =SUM(D8:D11) -> 10744.348 | E12: =SUM(E8:E11) -> 11281.578 | F12: =SUM(F8:F11) -> 11845.263
A14: DISCOUNT FACTORS & PV OF FCF
B15: 2024 | C15: 2025 | D15: 2026 | E15: 2027 | F15: 2028
A16: Discount Period | B16: 1 | C16: 2 | D16: 3 | E16: 4 | F16: 5
A17: Discount Factor [1/(1+WACC)^n] | B17: =1/((1+Assumptions!$B$17)^B16) -> 0.92421442 | C17: =1/((1+Assumptions!$B$17)^C16) -> 0.85417229 | D17: =1/((1+Assumptions!$B$17)^D16) -> 0.78943835 | E17: =1/((1+Assumptions!$B$17)^E16) -> 0.7296103 | F17: =1/((1+Assumptions!$B$17)^F16) -> 0.67431636
A18: PV of Free Cash Flow | B18: =B12*B17 -> 8894.1081 | C18: =C12*C17 -> 8740.54 | D18: =D12*D17 -> 8482.0003 | E18: =E12*E17 -> 8231.1555 | F18: =F12*F17 -> 7987.4546
A20: TERMINAL VALUE & ENTERPRISE VALUE
A21: Terminal Year FCF (Year 5) | B21: =F12 -> 11845.263
A22: Terminal Growth Rate (g) | B22: =Assumptions!$B$18 -> 0.025
A23: WACC | B23: =Assumptions!$B$17 -> 0.082
A24: Terminal Value [FCF*(1+g)/(WACC-g)] | B24: =B21*(1+B22)/(B23-B22) -> 213006.92
A25: PV of Terminal Value | B25: =B24*F17 -> 143634.05
A26: Sum of PV of FCFs | B26: =SUM(B18:F18) -> 42335.259
A27: Enterprise Value (EV) | B27: =B25+B26 -> 185969.31
A29: BRIDGE TO EQUITY VALUE
A30: Enterprise Value | B30: =B27 -> 185969.31
A31: Less: Total Debt | B31: -35547
A32: Add: Cash & Equivalents | B32: 9366
A33: Equity Value | B33: =B30+B31+B32 -> 159788.31
A34: Shares Outstanding (mm) | B34: 4320
A35: IMPLIED SHARE PRICE | B35: =B33/B34 -> 36.988035
A37: SENSITIVITY ANALYSIS — IMPLIED SHARE PRICE
A38: WACC \ Terminal Growth Rate | B38: 0.015 | C38: 0.02 | D38: 0.025 | E38: 0.03 | F38: 0.035
A39: 0.07 | B39: =(B21*(1+0.015)/(0.07-0.015)*1/((1+0.07)^5)+B26)+(B31+B32) -> 172012.28 | C39: =(B21*(1+0.02)/(0.07-0.02)*1/((1+0.07)^5)+B26)+(B31+B32) -> 188442.64 | D39: =(B21*(1+0.025)/(0.07-0.025)*1/((1+0.07)^5)+B26)+(B31+B32) -> 208524.18 | E39: =(B21*(1+0.03)/(0.07-0.03)*1/((1+0.07)^5)+B26)+(B31+B32) -> 233626.11 | F39: =(B21*(1+0.035)/(0.07-0.035)*1/((1+0.07)^5)+B26)+(B31+B32) -> 265900.02
A40: 0.075 | B40: =(B21*(1+0.015)/(0.075-0.015)*1/((1+0.075)^5)+B26)+(B31+B32) -> 155732.33 | C40: =(B21*(1+0.02)/(0.075-0.02)*1/((1+0.075)^5)+B26)+(B31+B32) -> 169171.32 | D40: =(B21*(1+0.025)/(0.075-0.025)*1/((1+0.075)^5)+B26)+(B31+B32) -> 185298.12 | E40: =(B21*(1+0.03)/(0.075-0.03)*1/((1+0.075)^5)+B26)+(B31+B32) -> 205008.65 | F40: =(B21*(1+0.035)/(0.075-0.035)*1/((1+0.075)^5)+B26)+(B31+B32) -> 229646.82
A41: 0.082 | B41: =(B21*(1+0.015)/(0.082-0.015)*1/((1+0.082)^5)+B26)+(B31+B32) -> 137158.24 | C41: =(B21*(1+0.02)/(0.082-0.02)*1/((1+0.082)^5)+B26)+(B31+B32) -> 147560.77 | D41: =(B21*(1+0.025)/(0.082-0.025)*1/((1+0.082)^5)+B26)+(B31+B32) -> 159788.31 | E41: =(B21*(1+0.03)/(0.082-0.03)*1/((1+0.082)^5)+B26)+(B31+B32) -> 174367.3 | F41: =(B21*(1+0.035)/(0.082-0.035)*1/((1+0.082)^5)+B26)+(B31+B32) -> 192048.21
A42: 0.09 | B42: =(B21*(1+0.015)/(0.09-0.015)*1/((1+0.09)^5)+B26)+(B31+B32) -> 120342.09 | C42: =(B21*(1+0.02)/(0.09-0.02)*1/((1+0.09)^5)+B26)+(B31+B32) -> 128333.98 | D42: =(B21*(1+0.025)/(0.09-0.025)*1/((1+0.09)^5)+B26)+(B31+B32) -> 137555.39 | E42: =(B21*(1+0.03)/(0.09-0.03)*1/((1+0.09)^5)+B26)+(B31+B32) -> 148313.7 | F42: =(B21*(1+0.035)/(0.09-0.035)*1/((1+0.09)^5)+B26)+(B31+B32) -> 161028.07
A43: 0.095 | B43: =(B21*(1+0.015)/(0.095-0.015)*1/((1+0.095)^5)+B26)+(B31+B32) -> 111620.58 | C43: =(B21*(1+0.02)/(0.095-0.02)*1/((1+0.095)^5)+B26)+(B31+B32) -> 118486.63 | D43: =(B21*(1+0.025)/(0.095-0.025)*1/((1+0.095)^5)+B26)+(B31+B32) -> 126333.54 | E43: =(B21*(1+0.03)/(0.095-0.03)*1/((1+0.095)^5)+B26)+(B31+B32) -> 135387.67 | F43: =(B21*(1+0.035)/(0.095-0.035)*1/((1+0.095)^5)+B26)+(B31+B32) -> 145950.83

Sheet Trading Comps
A1: COCA-COLA COMPANY — TRADING COMPARABLES ANALYSIS
A2: Market data as of FY2023 | USD Millions unless stated | EV = Enterprise Value
A4: Company | B4: Market Cap | C4: Net Debt | D4: EV | E4: Revenue | F4: EBITDA | G4: EV/Revenue | H4: EV/EBITDA | I4: P/E | J4: Net Margin
A5: Coca-Cola (KO) | B5: 265000 | C5: 26181 | D5: =B5+C5 -> 291181 | E5: 45754 | F5: 13177 | G5: =D5/E5 -> 6.3640556 | H5: =D5/F5 -> 22.09767 | I5: 24.1 | J5: 0.239
A6: PepsiCo (PEP) | B6: 238000 | C6: 28500 | D6: =B6+C6 -> 266500 | E6: 91471 | F6: 15800 | G6: =D6/E6 -> 2.9134917 | H6: =D6/F6 -> 16.867089 | I6: 23.5 | J6: 0.09
A7: Monster Beverage | B7: 54000 | C7: -2800 | D7: =B7+C7 -> 51200 | E7: 7140 | F7: 1820 | G7: =D7/E7 -> 7.1708683 | H7: =D7/F7 -> 28.131868 | I7: 31.2 | J7: 0.228
A8: Keurig Dr Pepper | B8: 48000 | C8: 11200 | D8: =B8+C8 -> 59200 | E8: 14812 | F8: 3520 | G8: =D8/E8 -> 3.9967594 | H8: =D8/F8 -> 16.818182 | I8: 22.8 | J8: 0.112
A9: Constellation Brands | B9: 43000 | C9: 11900 | D9: =B9+C9 -> 54900 | E9: 9650 | F9: 2480 | G9: =D9/E9 -> 5.6891192 | H9: =D9/F9 -> 22.137097 | I9: 20.1 | J9: 0.134
A11: COMPARABLE STATISTICS
A12: 25th Percentile | G12: =QUARTILE(G5:G9,1) -> 3.9967594 | H12: =QUARTILE(H5:H9,1) -> 16.867089 | I12: =QUARTILE(I5:I9,1) -> 22.8 | J12: =QUARTILE(J5:J9,1) -> 0.112
A13: Median | G13: =MEDIAN(G5:G9) -> 5.6891192 | H13: =MEDIAN(H5:H9) -> 22.09767 | I13: =MEDIAN(I5:I9) -> 23.5 | J13: =MEDIAN(J5:J9) -> 0.134
A14: Mean | G14: =AVERAGE(G5:G9) -> 5.2268588 | H14: =AVERAGE(H5:H9) -> 21.210381 | I14: =AVERAGE(I5:I9) -> 24.34 | J14: =AVERAGE(J5:J9) -> 0.1606
A15: 75th Percentile | G15: =QUARTILE(G5:G9,3) -> 6.3640556 | H15: =QUARTILE(H5:H9,3) -> 22.137097 | I15: =QUARTILE(I5:I9,3) -> 24.1 | J15: =QUARTILE(J5:J9,3) -> 0.228
A17: IMPLIED VALUATION — COCA-COLA
A18: Metric | B18: KO Value | C18: Median Multiple | D18: Implied EV | E18: Less: Net Debt | F18: Implied Eq. Value | G18: Shares (mm) | H18: Implied Price
A19: EV / Revenue | B19: 45754 | C19: =H13 -> 22.09767 | D19: =B19*C19 -> 1011056.8 | E19: 26181 | F19: =D19-E19 -> 984875.8 | G19: 4320 | H19: =F19/G19 -> 227.98051
A20: EV / EBITDA | B20: 13177 | C20: =I13 -> 23.5 | D20: =B20*C20 -> 309659.5 | E20: 26181 | F20: =D20-E20 -> 283478.5 | G20: 4320 | H20: =F20/G20 -> 65.620023

Sheet Valuation Summary
A1: COCA-COLA — VALUATION SUMMARY (FOOTBALL FIELD)
A2: Current Market Price: ~$60 | Analysis Date: FY2023
A4: Methodology | B4: Low ($) | C4: High ($) | D4: Comment
A5: DCF Valuation | B5: ='DCF Valuation'!B35*0.9 -> 33.289231 | C5: ='DCF Valuation'!B35*1.1 -> 40.686838 | D5: Base case WACC 8.2%, TGR 2.5%
A6: EV/Revenue (Trading Comp) | B6: ='Trading Comps'!H19 -> 227.98051 | C6: ='Trading Comps'!H19*1.15 -> 262.17759 | D6: Median peer multiple
A7: EV/EBITDA (Trading Comp) | B7: ='Trading Comps'!H20 -> 65.620023 | C7: ='Trading Comps'!H20*1.15 -> 75.463027 | D7: Median peer multiple
A8: 52-Week Range | B8: 55 | C8: 67.5 | D8: Market observed range
A10: INVESTMENT RECOMMENDATION
A11: HOLD / ACCUMULATE on dips. DCF and comparable analysis suggest fair value range of $55–$67. Strong brand moat, consistent dividend growth (60+ years), and emerging market expansion support long-term thesis. Current valuation appears fairly priced to slightly premium vs. peers.
