Workbook
Name Annual_Growth_Tapering: '[1]DCF Model'!$C$17
Name Annual_Growth_Tapering: DCF!$C$17
Name Tax_rate: '[1]DCF Model'!$C$22
Name UPDATE: 'Data Sheet'!$E$1

Sheet Data Sheet
A1: COMPANY NAME | B1: TRENT LTD | E1: =IF(B2<>B3, "A NEW VERSION OF THE WORKSHEET IS AVAILABLE", "")
A2: LATEST VERSION | B2: 2.1 | E2: PLEASE DO NOT MAKE ANY CHANGES TO THIS SHEET
A3: CURRENT VERSION | B3: 2.1
A5: META
A6: Number of shares | B6: =IF(B9>0, B9/B8, 0) -> 35.558215
A7: Face Value | B7: 1
A8: Current Price | B8: 3795.1
A9: Market Capitalization | B9: 134946.98
A15: PROFIT & LOSS
A16: Report Date | B16: 42460 | C16: 42825 | D16: 43190 | E16: 43555 | F16: 43921 | G16: 44286 | H16: 44651 | I16: 45016 | J16: 45382 | K16: 45747
A17: Sales | B17: 1686.17 | C17: 1812.44 | D17: 2157.46 | E17: 2630.24 | F17: 3485.98 | G17: 2592.96 | H17: 4498.02 | I17: 8242.02 | J17: 12375.11 | K17: 17134.61
A18: Raw Material Cost | B18: 810.2 | C18: 911.22 | D18: 1070.02 | E18: 1459.67 | F18: 1951.64 | G18: 1371.64 | H18: 2920.38 | I18: 5211.05 | J18: 7123.6 | K18: 10143.39
A19: Change in Inventory | B19: 14.59 | C19: 29.86 | D19: 38.51 | E19: 148.23 | F19: 69.89 | G19: -162.36 | H19: 438.84 | I19: 491.31 | J19: 164.71 | K19: 454.25
A20: Power and Fuel | B20: 48.92 | C20: 51.28 | D20: 52.75 | E20: 59.18 | F20: 66.64 | G20: 49.41 | H20: 71.89 | I20: 144.28 | J20: 229.16 | K20: 349.87
A21: Other Mfr. Exp | B21: 76.42 | C21: 81.91 | D21: 90.78 | E21: 122.09 | F21: 97.51 | G21: 92 | H21: 127.14 | I21: 211.99 | J21: 264.59 | K21: 369.79
A22: Employee Cost | B22: 165.69 | C22: 194.72 | D22: 233.02 | E22: 288.89 | F22: 361.01 | G22: 303.4 | H22: 402.92 | I22: 659.07 | J22: 1041.74 | K22: 1315.54
A23: Selling and admin | B23: 444.06 | C23: 407.07 | D23: 450.61 | E23: 514.41 | F23: 436.82 | G23: 364.62 | H23: 705.03 | I23: 1252.53 | J23: 1709.55 | K23: 2322.83
A24: Other Expenses | B24: 65.71 | C24: 62.57 | D24: 90.29 | E24: 93.59 | F24: 113.28 | G24: 135.66 | H24: 114.78 | I24: 140.26 | J24: 200.49 | K24: 267.48
A25: Other Income | B25: 86.44 | C25: 81.31 | D25: 27.47 | E25: 30.14 | F25: 146.63 | G25: 199.4 | H25: 152.16 | I25: 340.6 | J25: 988.91 | K25: 305.06
A26: Depreciation | B26: 38.59 | C26: 41.29 | D26: 45.53 | E26: 51.67 | F26: 247.24 | G26: 257.3 | H26: 310.82 | I26: 493.69 | J26: 671.11 | K26: 895.18
A27: Interest | B27: 47.73 | C27: 45.55 | D27: 43.78 | E27: 50.64 | F27: 263.37 | G27: 260.79 | H27: 324.84 | I27: 408.99 | J27: 367.66 | K27: 200.1
... A31: Dividend Amount | B31: 29.91 | C31: 33.23 | D31: 38.21 | E31: 43.2 | F31: 35.55 | G31: 21.33 | H31: 60.44 | I31: 78.21 | J31: 113.76 | K31: 177.75
A40: Quarters
A41: Report Date | B41: 45107 | C41: 45199 | D41: 45291 | E41: 45382 | F41: 45473 | G41: 45565 | H41: 45657 | I41: 45747 | J41: 45838 | K41: 45930
A42: Sales | B42: 2628.37 | C42: 2982.42 | D42: 3466.62 | E42: 3297.7 | F42: 4104.44 | G42: 4156.67 | H42: 4656.56 | I42: 4216.94 | J42: 4883.48 | K42: 4817.68
A43: Expenses | B43: 2260.97 | C43: 2525.85 | D43: 2838.1 | E43: 2828.06 | F43: 3491.09 | G43: 3510.95 | H43: 3809.19 | I43: 3566.03 | J43: 4035.62 | K43: 4001.7
A44: Other Income | B44: 78.61 | C44: 105.42 | D44: 110.01 | E44: 694.87 | F44: 100.91 | G44: 51.04 | H44: 79.87 | I44: 74.34 | J44: 49.8 | K44: 27.55
A45: Depreciation | B45: 141.42 | C45: 152.22 | D45: 164.53 | E45: 212.94 | F45: 181.32 | G45: 196.95 | H45: 244.93 | I45: 271.98 | J45: 292.93 | K45: 324.93
A46: Interest | B46: 92.3 | C46: 95.45 | D46: 98.81 | E46: 32.54 | F46: 31.55 | G46: 33 | H46: 36.52 | I46: 37.52 | J46: 40.04 | K46: 41.62
A47: Profit before tax | B47: 212.29 | C47: 314.32 | D47: 475.19 | E47: 919.03 | F47: 501.39 | G47: 466.81 | H47: 645.79 | I47: 415.75 | J47: 564.69 | K47: 476.98
A48: Tax | B48: 45.62 | C48: 86.26 | D48: 104.55 | E48: 206.94 | F48: 110.18 | G48: 131.75 | H48: 149.25 | I48: 104.15 | J48: 139.99 | K48: 103.56
A49: Net profit | B49: 173.48 | C49: 234.73 | D49: 374.36 | E49: 704.23 | F49: 392.57 | G49: 338.75 | H49: 497.25 | I49: 318.15 | J49: 429.69 | K49: 376.86
A50: Operating Profit | B50: 367.4 | C50: 456.57 | D50: 628.52 | E50: 469.64 | F50: 613.35 | G50: 645.72 | H50: 847.37 | I50: 650.91 | J50: 847.86 | K50: 815.98
A55: BALANCE SHEET
A56: Report Date | B56: 42460 | C56: 42825 | D56: 43190 | E56: 43555 | F56: 43921 | G56: 44286 | H56: 44651 | I56: 45016 | J56: 45382 | K56: 45747
A57: Equity Share Capital | B57: 33.23 | C57: 33.23 | D57: 33.23 | E57: 33.23 | F57: 35.55 | G57: 35.55 | H57: 35.55 | I57: 35.55 | J57: 35.55 | K57: 35.55
A58: Reserves | B58: 1431.16 | C58: 1514.46 | D58: 1562.14 | E58: 1613.28 | F58: 2352.22 | G58: 2277.48 | H58: 2328.45 | I58: 2559.94 | J58: 4032.19 | K58: 5426.19
A59: Borrowings | B59: 399.8 | C59: 391.74 | D59: 391.43 | E59: 494.14 | F59: 299.74 | G59: 299.93 | H59: 4725.36 | I59: 4464.14 | J59: 1752.99 | K59: 2237.19
A60: Other Liabilities | B60: 292.4 | C60: 282.82 | D60: 349.06 | E60: 418.11 | F60: 2819.17 | G60: 3110.77 | H60: 636.66 | I60: 1021.9 | J60: 1341.02 | K60: 1720.71
A61: Total | B61: 2156.59 | C61: 2222.25 | D61: 2335.86 | E61: 2558.76 | F61: 5506.68 | G61: 5723.73 | H61: 7726.02 | I61: 8081.53 | J61: 7161.75 | K61: 9419.64
A62: Net Block | B62: 476.79 | C62: 548.71 | D62: 612.53 | E62: 662.18 | F62: 2738.43 | G62: 3053.82 | H62: 4686.71 | I62: 4526.95 | J62: 2449.92 | K62: 3895.13
A63: Capital Work in Progress | B63: 54.86 | C63: 5.48 | D63: 9.59 | E63: 87.18 | F63: 23.32 | G63: 107.98 | H63: 104.72 | I63: 101.72 | J63: 223.78 | K63: 179.5
A64: Investments | B64: 1066.97 | C64: 1079.96 | D64: 1022.88 | E64: 882.83 | F64: 1514.78 | G64: 1487.29 | H64: 1283.72 | I64: 1109.87 | J64: 1416.03 | K64: 1480.25
A65: Other Assets | B65: 557.97 | C65: 588.1 | D65: 690.86 | E65: 926.57 | F65: 1230.15 | G65: 1074.64 | H65: 1650.87 | I65: 2342.99 | J65: 3072.02 | K65: 3864.76
A66: Total | B66: 2156.59 | C66: 2222.25 | D66: 2335.86 | E66: 2558.76 | F66: 5506.68 | G66: 5723.73 | H66: 7726.02 | I66: 8081.53 | J66: 7161.75 | K66: 9419.64
A67: Receivables | B67: 12.99 | C67: 5.92 | D67: 15.1 | E67: 16.54 | F67: 17.12 | G67: 20.77 | H67: 18.26 | I67: 34.39 | J67: 81.74 | K67: 62.95
... A70: No. of Equity Shares | B70: 33231673 | C70: 332316730 | D70: 332316730 | E70: 332316730 | F70: 355487461 | G70: 355487461 | H70: 355487461 | I70: 355487461 | J70: 355487461 | K70: 355487461
A71: New Bonus Shares
A72: Face value | B72: 10 | C72: 1 | D72: 1 | E72: 1 | F72: 1 | G72: 1 | H72: 1 | I72: 1 | J72: 1 | K72: 1
A80: CASH FLOW:
A81: Report Date | B81: 42460 | C81: 42825 | D81: 43190 | E81: 43555 | F81: 43921 | G81: 44286 | H81: 44651 | I81: 45016 | J81: 45382 | K81: 45747
A82: Cash from Operating Activity | B82: 109.42 | C82: 102.44 | D82: 76.86 | E82: 20.98 | F82: 361.16 | G82: 285.03 | H82: 58.08 | I82: 594.88 | J82: 1348.98 | K82: 1660.9
A83: Cash from Investing Activity | B83: -98.4 | C83: -43.7 | D83: -4.02 | E83: -37.03 | F83: -808.56 | G83: 17.71 | H83: 56.03 | I83: -102.63 | J83: -508.21 | K83: -923.31
A84: Cash from Financing Activity | B84: -13.33 | C84: -51.36 | D84: -74.31 | E84: 37.47 | F84: 451.94 | G84: -283.11 | H84: -107.98 | I84: -491.41 | J84: -629.45 | K84: -693.67
A85: Net Cash Flow | B85: -2.31 | C85: 7.38 | D85: -1.47 | E85: 21.42 | F85: 4.54 | G85: 19.63 | H85: 6.13 | I85: 0.84 | J85: 211.32 | K85: 43.92
H86: =SUM(G67:G68)-SUM(H67:H68) -> -436.88 | I86: =SUM(H67:H68)-SUM(I67:I68) -> -509.51 | J86: =SUM(I67:I68)-SUM(J67:J68) -> -268.92 | K86: =SUM(J67:J68)-SUM(K67:K68) -> -443.53
H87: =SUM(H83,H86) -> -380.85 | I87: =SUM(I83,I86) -> -612.14 | J87: =SUM(J83,J86) -> -777.13 | K87: =SUM(K83,K86) -> -1366.84
A88: NOPAT | H88: ='[1]DCF Model'!D39*(1-Tax_rate) -> 212.925 | I88: ='[1]DCF Model'!E39*(1-Tax_rate) -> 465.345 | J88: ='[1]DCF Model'!F39*(1-Tax_rate) -> 974.685 | K88: ='[1]DCF Model'!G39*(1-Tax_rate) -> 1443.585
H89: =H87/H88 -> -1.788658 | I89: =I87/I88 -> -1.3154541 | J89: =J87/J88 -> -0.797314 | K89: =K87/K88 -> -0.94683721
A93: PRICE: | B93: 159.18 | C93: 266.7 | D93: 345.05 | E93: 361.9 | F93: 484.35 | G93: 751.05 | H93: 1275.5 | I93: 1374.95 | J93: 3948 | K93: 5325.15
A95: DERIVED:
A96: Adjusted Equity Shares in Cr | B96: 33.23 | C96: 33.23 | D96: 33.23 | E96: 33.23 | F96: 35.55 | G96: 35.55 | H96: 35.55 | I96: 35.55 | J96: 35.55 | K96: 35.55

Sheet DCF
B5: Trent limited
B6: Company Overview
B7: Trent, part of the Tata Group, operates a variety of retail chains in India, including department
B8: stores, hypermarkets, supermarkets, and specialty stores. Trent operates under several brand
B9: names like Zudio, Westside, Zara, Massimo Dutti, and Utsa. The company serves customers
B10: through both physical stores and online platforms.
B13: Parameter | C13: Value | D13: Rationale
B14: Vauation Date
B15: Projection Period
B16: Revenue Growth% | C16: 0.21 | D16: Economic Times highlights execution constraints to achieve 25% growth in the remaining quarter; revenue growth assumed at 18–22%.
B17: Annual Growth Tapering | C17: 0.02
B19: Terminal Growth Rate | C19: 0.06 | D19: Conservative long- term growth considering india's GDP and retail sector potential
B20: Risk-free Rate (Rf) | C20: 0.067 | D20: 10 year indian Government Bond yied
B21: Equity Risk Premium(ERP) | C21: 0.055 | D21: equity risk premium
B22: Tax Rate | C22: 0.25
B24: Financial Performance (₹ Crore)
B25: INCOME STATEMENT
B26: Particulars | C26: 2021 | D26: =C26+1 -> 2022 | E26: =D26+1 -> 2023 | F26: =E26+1 -> 2024 | G26: =F26+1 -> 2025
B27: Sales | C27: ='Data Sheet'!G17 -> 2592.96 | D27: ='Data Sheet'!H17 -> 4498.02 | E27: ='Data Sheet'!I17 -> 8242.02 | F27: ='Data Sheet'!J17 -> 12375.11 | G27: ='Data Sheet'!K17 -> 17134.61 | H27: CAGR
B28: % growth | D28: =(D27/C27)-1 -> 0.73470474 | E28: =(E27/D27)-1 -> 0.83236624 | F28: =(F27/E27)-1 -> 0.50146566 | G28: =(G27/F27)-1 -> 0.38460264 | H28: =_xlfn.RRI(4,C27,G27) -> 0.60331775
B29: Cost of Goods Sold | C29: =SUM('Data Sheet'!G18,'Data Sheet'!G20:G21)-'Data Sheet'!G19 -> 1675.41 | D29: =SUM('Data Sheet'!H18,'Data Sheet'!H20:H21)-'Data Sheet'!H19 -> 2680.57 | E29: =SUM('Data Sheet'!I18,'Data Sheet'!I20:I21)-'Data Sheet'!I19 -> 5076.01 | F29: =SUM('Data Sheet'!J18,'Data Sheet'!J20:J21)-'Data Sheet'!J19 -> 7452.64 | G29: =SUM('Data Sheet'!K18,'Data Sheet'!K20:K21)-'Data Sheet'!K19 -> 10408.8
B30: % of revenue | C30: =C29/C27 -> 0.646138 | D30: =D29/D27 -> 0.59594444 | E30: =E29/E27 -> 0.61586965 | F30: =F29/F27 -> 0.60222818 | G30: =G29/G27 -> 0.60747224
B31: Gross Profit | C31: =C27-C29 -> 917.55 | D31: =D27-D29 -> 1817.45 | E31: =E27-E29 -> 3166.01 | F31: =F27-F29 -> 4922.47 | G31: =G27-G29 -> 6725.81
B32: % margin | C32: =C31/C27 -> 0.353862 | D32: =D31/D27 -> 0.40405556 | E32: =E31/E27 -> 0.38413035 | F32: =F31/F27 -> 0.39777182 | G32: =G31/G27 -> 0.39252776
B33: Operating Expenses | C33: =SUM('Data Sheet'!G22:G24) -> 803.68 | D33: =SUM('Data Sheet'!H22:H24) -> 1222.73 | E33: =SUM('Data Sheet'!I22:I24) -> 2051.86 | F33: =SUM('Data Sheet'!J22:J24) -> 2951.78 | G33: =SUM('Data Sheet'!K22:K24) -> 3905.85
B34: % of revenue | C34: =C33/C27 -> 0.30994693 | D34: =D33/D27 -> 0.27183739 | E34: =E33/E27 -> 0.24895111 | F34: =F33/F27 -> 0.23852556 | G34: =G33/G27 -> 0.22795091
B35: EBITDA | C35: =C31-C33 -> 113.87 | D35: =D31-D33 -> 594.72 | E35: =E31-E33 -> 1114.15 | F35: =F31-F33 -> 1970.69 | G35: =G31-G33 -> 2819.96
B36: % margin | C36: =C35/C27 -> 0.043915062 | D36: =D35/D27 -> 0.13221818 | E36: =E35/E27 -> 0.13517924 | F36: =F35/F27 -> 0.15924626 | G36: =G35/G27 -> 0.16457684
B37: Depreciation | C37: ='Data Sheet'!G26 -> 257.3 | D37: ='Data Sheet'!H26 -> 310.82 | E37: ='Data Sheet'!I26 -> 493.69 | F37: ='Data Sheet'!J26 -> 671.11 | G37: ='Data Sheet'!K26 -> 895.18
B38: % of revenue | C38: =C37/C27 -> 0.099230223 | D38: =D37/D27 -> 0.069101516 | E38: =E37/E27 -> 0.059899151 | F38: =F37/F27 -> 0.054230629 | G38: =G37/G27 -> 0.052243967
B39: EBIT | C39: =C35-C37 -> -143.43 | D39: =D35-D37 -> 283.9 | E39: =E35-E37 -> 620.46 | F39: =F35-F37 -> 1299.58 | G39: =G35-G37 -> 1924.78
B40: % margin | C40: =C39/C27 -> -0.055315161 | D40: =D39/D27 -> 0.06311666 | E40: =E39/E27 -> 0.075280089 | F40: =F39/F27 -> 0.10501563 | G40: =G39/G27 -> 0.11233287
B41: Other Income | C41: ='Data Sheet'!G25 -> 199.4 | D41: ='Data Sheet'!H25 -> 152.16 | E41: ='Data Sheet'!I25 -> 340.6 | F41: ='Data Sheet'!J25 -> 988.91 | G41: ='Data Sheet'!K25 -> 305.06
B42: Interest | C42: ='Data Sheet'!G27 -> 260.79 | D42: ='Data Sheet'!H27 -> 324.84 | E42: ='Data Sheet'!I27 -> 408.99 | F42: ='Data Sheet'!J27 -> 367.66 | G42: ='Data Sheet'!K27 -> 200.1
B43: % of debt | C43: =C42/'Data Sheet'!G60 -> 0.083834549 | D43: =D42/'Data Sheet'!H60 -> 0.51022524 | E43: =E42/'Data Sheet'!I60 -> 0.40022507 | F43: =F42/'Data Sheet'!J60 -> 0.27416444 | G43: =G42/'Data Sheet'!K60 -> 0.11628921
B44: Profit before tax | C44: =C39+C41-C42 -> -204.82 | D44: =D39+D41-D42 -> 111.22 | E44: =E39+E41-E42 -> 552.07 | F44: =F39+F41-F42 -> 1920.83 | G44: =G39+G41-G42 -> 2029.74
B45: % of revenue | C45: =C44/C27 -> -0.078990806 | D45: =D44/D27 -> 0.024726435 | E45: =E44/E27 -> 0.066982366 | F45: =F44/F27 -> 0.15521721 | G45: =G44/G27 -> 0.11845849
B46: Tax | C46: ='Data Sheet'!G29 -> -23.69 | D46: ='Data Sheet'!H29 -> 76.62 | E46: ='Data Sheet'!I29 -> 158.44 | F46: ='Data Sheet'!J29 -> 443.37 | G46: ='Data Sheet'!K29 -> 495.33
B47: % of PBT | C47: =C46/C44 -> 0.11566253 | D47: =D46/D44 -> 0.68890487 | E47: =E46/E44 -> 0.28699259 | F47: =F46/F44 -> 0.23082209 | G47: =G46/G44 -> 0.24403618
B48: Net profit | C48: =C44-C46 -> -181.13 | D48: =D44-D46 -> 34.6 | E48: =E44-E46 -> 393.63 | F48: =F44-F46 -> 1477.46 | G48: =G44-G46 -> 1534.41
B49: % of revenue | C49: =C48/C27 -> -0.069854529 | D49: =D48/D27 -> 0.0076922735 | E49: =E48/E27 -> 0.047758923 | F49: =F48/F27 -> 0.11938965 | G49: =G48/G27 -> 0.089550331
B51: BALANCE SHEET
B52: Particulars | C52: 2021 | D52: =C52+1 -> 2022 | E52: =D52+1 -> 2023 | F52: =E52+1 -> 2024 | G52: =F52+1 -> 2025
B53: Equity Share Capital | C53: ='Data Sheet'!G57 -> 35.55 | D53: ='Data Sheet'!H57 -> 35.55 | E53: ='Data Sheet'!I57 -> 35.55 | F53: ='Data Sheet'!J57 -> 35.55 | G53: ='Data Sheet'!K57 -> 35.55
B54: Reserves | C54: ='Data Sheet'!G58 -> 2277.48 | D54: ='Data Sheet'!H58 -> 2328.45 | E54: ='Data Sheet'!I58 -> 2559.94 | F54: ='Data Sheet'!J58 -> 4032.19 | G54: ='Data Sheet'!K58 -> 5426.19
B55: Borrowings | C55: ='Data Sheet'!G59 -> 299.93 | D55: ='Data Sheet'!H59 -> 4725.36 | E55: ='Data Sheet'!I59 -> 4464.14 | F55: ='Data Sheet'!J59 -> 1752.99 | G55: ='Data Sheet'!K59 -> 2237.19
B56: Other Liabilities | C56: ='Data Sheet'!G60 -> 3110.77 | D56: ='Data Sheet'!H60 -> 636.66 | E56: ='Data Sheet'!I60 -> 1021.9 | F56: ='Data Sheet'!J60 -> 1341.02 | G56: ='Data Sheet'!K60 -> 1720.71
B57: Total | C57: =SUM(C53:C56) -> 5723.73 | D57: =SUM(D53:D56) -> 7726.02 | E57: =SUM(E53:E56) -> 8081.53 | F57: =SUM(F53:F56) -> 7161.75 | G57: =SUM(G53:G56) -> 9419.64
B58: Net Block | C58: ='Data Sheet'!G62 -> 3053.82 | D58: ='Data Sheet'!H62 -> 4686.71 | E58: ='Data Sheet'!I62 -> 4526.95 | F58: ='Data Sheet'!J62 -> 2449.92 | G58: ='Data Sheet'!K62 -> 3895.13
B59: Capital Work in Progress | C59: ='Data Sheet'!G63 -> 107.98 | D59: ='Data Sheet'!H63 -> 104.72 | E59: ='Data Sheet'!I63 -> 101.72 | F59: ='Data Sheet'!J63 -> 223.78 | G59: ='Data Sheet'!K63 -> 179.5
B60: Investments | C60: ='Data Sheet'!G64 -> 1487.29 | D60: ='Data Sheet'!H64 -> 1283.72 | E60: ='Data Sheet'!I64 -> 1109.87 | F60: ='Data Sheet'!J64 -> 1416.03 | G60: ='Data Sheet'!K64 -> 1480.25
B61: Receivables | C61: ='Data Sheet'!G67 -> 20.77 | D61: ='Data Sheet'!H67 -> 18.26 | E61: ='Data Sheet'!I67 -> 34.39 | F61: ='Data Sheet'!J67 -> 81.74 | G61: ='Data Sheet'!K67 -> 62.95
B62: Inventory | C62: ='Data Sheet'!G68 -> 428.39 | D62: ='Data Sheet'!H68 -> 867.78 | E62: ='Data Sheet'!I68 -> 1361.16 | F62: ='Data Sheet'!J68 -> 1582.73 | G62: ='Data Sheet'!K68 -> 2045.05
B63: Cash & Bank | C63: ='Data Sheet'!G69 -> 81.47 | D63: ='Data Sheet'!H69 -> 85.97 | E63: ='Data Sheet'!I69 -> 86.3 | F63: ='Data Sheet'!J69 -> 297.56 | G63: ='Data Sheet'!K69 -> 339.84
B64: Other Assets | C64: ='Data Sheet'!G65-SUM('Data Sheet'!G67:G69) -> 544.01 | D64: ='Data Sheet'!H65-SUM('Data Sheet'!H67:H69) -> 678.86 | E64: ='Data Sheet'!I65-SUM('Data Sheet'!I67:I69) -> 861.14 | F64: ='Data Sheet'!J65-SUM('Data Sheet'!J67:J69) -> 1109.99 | G64: ='Data Sheet'!K65-SUM('Data Sheet'!K67:K69) -> 1416.92
B65: Total | C65: =SUM(C58:C64) -> 5723.73 | D65: =SUM(D58:D64) -> 7726.02 | E65: =SUM(E58:E64) -> 8081.53 | F65: =SUM(F58:F64) -> 7161.75 | G65: =SUM(G58:G64) -> 9419.64
B67: Revenue Projections & Growth Assumptions
B68: Particulars | C68: 26 | D68: =C68+1 -> 27 | E68: =D68+1 -> 28 | F68: =E68+1 -> 29 | G68: =F68+1 -> 30
B69: Revenue Growth % | C69: {=CHOOSE(D71,C72:G72,C73:G73,C74:G74)} -> 0.21 | D69: 0.19 | E69: 0.17 | F69: 0.15 | G69: 0.13
B70: Revenue (in Crs.) | C70: =G27*(1+C69) -> 20732.878 | D70: =C70*(1+D69) -> 24672.125 | E70: =D70*(1+E69) -> 28866.386 | F70: =E70*(1+F69) -> 33196.344 | G70: =F70*(1+G69) -> 37511.869
C71: Base Case | D71: =MATCH(C71,B72:B74,0) -> 1
B72: Base Case | C72: =C16 -> 0.21 | D72: =C72-$C$17 -> 0.19 | E72: =D72-$C$17 -> 0.17 | F72: =E72-$C$17 -> 0.15 | G72: =F72-$C$17 -> 0.13
B73: Best Case | C73: =C72+4% -> 0.25 | D73: =C73-$C$17 -> 0.23 | E73: =D73-$C$17 -> 0.21 | F73: =E73-$C$17 -> 0.19 | G73: =F73-$C$17 -> 0.17
B74: Worst Case | C74: =C72-4% -> 0.17 | D74: =C74-Annual_Growth_Tapering -> 0.15 | E74: =D74-Annual_Growth_Tapering -> 0.13 | F74: =E74-Annual_Growth_Tapering -> 0.11 | G74: =F74-Annual_Growth_Tapering -> 0.09
B76: Free Cash Flow Projections (₹ Crores)
B77: Particulars | C77: 26 | D77: =C77+1 -> 27 | E77: =D77+1 -> 28 | F77: =E77+1 -> 29 | G77: =F77+1 -> 30
B78: Revenue | C78: =C70 -> 20732.878 | D78: =D70 -> 24672.125 | E78: =E70 -> 28866.386 | F78: =F70 -> 33196.344 | G78: =G70 -> 37511.869
B79: EBITDA Margin % | C79: =G36 -> 0.16457684 | D79: =C79 -> 0.16457684 | E79: =D79 -> 0.16457684 | F79: =E79 -> 0.16457684 | G79: =F79 -> 0.16457684
B80: EBITDA | C80: =C78*C79 -> 3412.1516 | D80: =D78*D79 -> 4060.4604 | E80: =E78*E79 -> 4750.7387 | F80: =F78*F79 -> 5463.3495 | G80: =G78*G79 -> 6173.5849
B81: Less: Depreciation | C81: =C78*AVERAGE($C$38:$G$38) -> 1387.8816 | D81: =D78*AVERAGE($C$38:$G$38) -> 1651.5791 | E81: =E78*AVERAGE($C$38:$G$38) -> 1932.3476 | F81: =F78*AVERAGE($C$38:$G$38) -> 2222.1997 | G81: =G78*AVERAGE($C$38:$G$38) -> 2511.0857
B82: EBIT | C82: =C80-C81 -> 2024.27 | D82: =D80-D81 -> 2408.8813 | E82: =E80-E81 -> 2818.3911 | F82: =F80-F81 -> 3241.1498 | G82: =G80-G81 -> 3662.4992
B83: Less: Tax | C83: =C82*Tax_rate -> 506.0675 | D83: =D82*Tax_rate -> 602.22032 | E83: =E82*Tax_rate -> 704.59778 | F83: =F82*Tax_rate -> 810.28744 | G83: =G82*Tax_rate -> 915.62481
B84: NOPAT | C84: =C82-C83 -> 1518.2025 | D84: =D82-D83 -> 1806.661 | E84: =E82-E83 -> 2113.7933 | F84: =F82-F83 -> 2430.8623 | G84: =G82-G83 -> 2746.8744
B85: Add: Depreciation | C85: =C81 -> 1387.8816 | D85: =D81 -> 1651.5791 | E85: =E81 -> 1932.3476 | F85: =F81 -> 2222.1997 | G85: =G81 -> 2511.0857
B86: Less: Reinvestment (Asssumption @50%) | C86: =-C84*50% -> -759.10125 | D86: =-D84*50% -> -903.33048 | E86: =-E84*50% -> -1056.8967 | F86: =-F84*50% -> -1215.4312 | G86: =-G84*50% -> -1373.4372
B87: Free Cash Flow to the Firm | C87: =SUM(C84:C86) -> 2146.9829 | D87: =SUM(D84:D86) -> 2554.9096 | E87: =SUM(E84:E86) -> 2989.2442 | F87: =SUM(F84:F86) -> 3437.6309 | G87: =SUM(G84:G86) -> 3884.5229
B89: Weighted Average Cost of Capital
B91: All figures are in INR unless stated otherwise
B93: Peer Comps
G94: Debt/ | H94: Debt/ | I94: Levered | J94: Unlevered
B95: Name of the Comp | C95: Country | D95: Total Debt | E95: Total equity | F95: Tax rate 1 | G95: Equity | H95: Capital | I95: Beta 2 | J95: Beta 3
B97: Trent Limited | C97: India | D97: ='Beta - Comps'!F6 -> 2348.57 | E97: ='Beta - Comps'!E6 -> 132557.77 | F97: =Tax_rate -> 0.25 | G97: =D97/E97 -> 0.017717332 | H97: =D97/(D97+E97) -> 0.017408893 | I97: ='Trent- Beta Regression'!$M$13 -> -0.3533564 | J97: =I97/(1+(1-F97)*G97) -> -0.34872257
B98: Avenue Supermarkets (Dmart) | C98: India | D98: ='Beta - Comps'!F7 -> 1609.19 | E98: ='Beta - Comps'!E7 -> 235270.19 | F98: =Tax_rate -> 0.25 | G98: =D98/E98 -> 0.0068397531 | H98: =D98/(D98+E98) -> 0.0067932886 | I98: ='DMART- Beta Regression'!M13 -> 0.9679798 | J98: =I98/(1+(1-F98)*G98) -> 0.96303958
B99: Vishal Mega Mart | C99: India | D99: ='Beta - Comps'!F8 -> 1870.76 | E99: ='Beta - Comps'!E8 -> 58187.97 | F99: =Tax_rate -> 0.25 | G99: =D99/E99 -> 0.032150288 | H99: =D99/(D99+E99) -> 0.031148844 | I99: ='VMM - Beta Regression '!$M$13 -> 1.2186694 | J99: =I99/(1+(1-F99)*G99) -> 1.1899758
B100: Aditya Birla Lifestyle Brands | C100: India | D100: ='Beta - Comps'!F9 -> 5665.24 | E100: ='Beta - Comps'!E9 -> 7909.96 | F100: =Tax_rate -> 0.25 | G100: =D100/E100 -> 0.71621601 | H100: =D100/(D100+E100) -> 0.41732277 | I100: ='ABLBL- Beta Regression'!M13 -> 1.6753739 | J100: =I100/(1+(1-F100)*G100) -> 1.0899137
B101: Vedant Fashions (Manyavar) | C101: India | D101: ='Beta - Comps'!F10 -> 463.76 | E101: ='Beta - Comps'!E10 -> 11627.44 | F101: =Tax_rate -> 0.25 | G101: =D101/E101 -> 0.039884962 | H101: =D101/(D101+E101) -> 0.038355167 | I101: ='Manyavar- Beta Regression'!M13 -> -0.19132287 | J101: =I101/(1+(1-F101)*G101) -> -0.18576592
E103: Average | F103: =AVERAGE(F97:F101) -> 0.25 | G103: =AVERAGE(G97:G101) -> 0.16256167 | H103: =AVERAGE(H97:H101) -> 0.10220579 | I103: =AVERAGE(I97:I101) -> 0.66346876 | J103: =AVERAGE(J97:J101) -> 0.54168812
E104: Median | F104: =MEDIAN(F97:F101) -> 0.25 | G104: =MEDIAN(G97:G101) -> 0.032150288 | H104: =MEDIAN(H97:H101) -> 0.031148844 | I104: =MEDIAN(I97:I101) -> 0.9679798 | J104: =MEDIAN(J97:J101) -> 0.96303958
B107: Cost of Debt | G107: Cost of Equity
B108: Pre-Tax Cost of Debt | E108: =200/2348.57 -> 0.085158203
B109: Tax rate | E109: =F101 -> 0.25 | G109: Risk Free Rate | J109: =C20 -> 0.067
B110: Post Tax Cost of Debt | E110: =E108*(1-E109) -> 0.063868652 | G110: Equity risk Premium | J110: =C21 -> 0.055
G111: Levered Beta 4 | J111: =J120 -> 1.0452646
G112: Cost of Equity | J112: =J109+J110*J111 -> 0.12448955
B115: Capital Structure | G115: Levered Beta
D117: Current | E117: Target | G117: Comps Median Unlevered Beta | J117: =J104 -> 0.96303958
B118: Total Debt | C118: =D97 -> 2348.57 | D118: =C118/$C$120 -> 0.017408893 | E118: =H103 -> 0.10220579 | G118: Target Debt/ Equity | J118: =E122 -> 0.113841
B119: Market Capitalization | C119: =E97 -> 132557.77 | D119: =C119/$C$120 -> 0.98259111 | E119: =E120-E118 -> 0.89779421 | G119: Tax rate | J119: =Tax_rate -> 0.25
B120: Total Capital | C120: =SUM(C118:C119) -> 134906.34 | D120: =C37/$C$37 -> 1 | E120: =D120 -> 1 | G120: Levered Beta | J120: =J117*(1+(1-J119)*J118) -> 1.0452646
B122: Debt/Equity | D122: =D118/D119 -> 0.017717332 | E122: =E118/E119 -> 0.113841 | G122: Weighted Average Cost of Capital
...

Sheet Beta - Comps
B5: S.No. | C5: Name | D5: CMP Rs. | E5: Mar Cap Rs.Cr. | F5: Debt Rs.Cr. | G5: Debt / Eq
B6: 1 | C6: Trent | D6: 3729 | E6: 132557.77 | F6: 2348.57 | G6: 0.38
B7: 2 | C7: Avenue Super. | D7: 3613.7 | E7: 235270.19 | F7: 1609.19 | G7: 0.07
B8: 3 | C8: Vishal Mega Mart | D8: 124.47 | E8: 58187.97 | F8: 1870.76 | G8: 0.27
B9: 4 | C9: Aditya Bir. Fas. | D9: 64.78 | E9: 7909.96 | F9: 5665.24 | G9: 0.91
B10: 5 | C10: Vedant Fashions | D10: 478.45 | E10: 11627.44 | F10: 463.76 | G10: 0.27

Sheet Raw FS
B5: Particulars | C5: 41699 | D5: 42064 | E5: 42430 | F5: 42795 | G5: 43160 | H5: 43525 | I5: 43891 | J5: 44256 | K5: 44621 | L5: 44986 | M5: 45352 | N5: 45717
B7: Equity Capital | C7: 33 | D7: 33 | E7: 33 | F7: 33 | G7: 33 | H7: 33 | I7: 36 | J7: 36 | K7: 36 | L7: 36 | M7: 36 | N7: 36
B8: Reserves | C8: 958 | D8: 1389 | E8: 1431 | F8: 1514 | G8: 1562 | H8: 1613 | I8: 2352 | J8: 2277 | K8: 2328 | L8: 2560 | M8: 4032 | N8: 5426
B9: Borrowings -
B10: Long term Borrowings | C10: 325 | D10: 112 | E10: 96 | H10: 300 | I10: 300 | J10: 0 | K10: 497 | L10: 498 | M10: 499 | N10: 499
B11: Short term Borrowings | C11: 7 | D11: 4 | E11: 4 | H11: 95 | I11: 0 | J11: 300 | K11: 0 | L11: 0 | M11: 0 | N11: 0
B12: Lease Liabilities | C12: 0 | D12: 0 | E12: 0 | F12: 0 | G12: 0 | H12: 0 | I12: 0 | J12: 2664 | K12: 4228 | L12: 3966 | M12: 1254 | N12: 1738
B13: Other Borrowings | C13: 0 | D13: 150 | E13: 300 | F13: 392 | G13: 391 | H13: 100 | I13: 0 | J13: -2664 | K13: 0 | L13: 0 | M13: 0 | N13: 0
B14: Other Liabilities -
B15: Non controlling int | C15: 3 | D15: 3 | E15: 10 | F15: 1 | G15: 1 | H15: -3 | I15: 80 | J15: 44 | K15: 46 | L15: 67 | M15: 35 | N15: 122
B16: Trade Payables | C16: 331 | D16: 221 | E16: 166 | F16: 169 | G16: 208 | H16: 245 | I16: 298 | J16: 275 | K16: 378 | L16: 665 | M16: 774 | N16: 928
B17: Other liability items | C17: 280 | D17: 294 | E17: 116 | F17: 113 | G17: 140 | H17: 176 | I17: 2442 | J17: 2792 | K17: 213 | L17: 289 | M17: 532 | N17: 671
B18: Total Liabilities | C18: 1936 | D18: 2207 | E18: 2157 | F18: 2222 | G18: 2336 | H18: 2559 | I18: 5507 | J18: 5724 | K18: 7726 | L18: 8082 | M18: 7162 | N18: 9420
B20: Fixed Assets -
B21: Land | C21: 63 | D21: 101 | E21: 58 | F21: 58 | G21: 61 | H21: 63 | I21: 63 | J21: 63 | K21: 62 | L21: 77 | M21: 86 | N21: 86
B22: Building | C22: 272 | D22: 232 | E22: 291 | F22: 326 | G22: 360 | H22: 382 | I22: 2622 | J22: 3117 | K22: 4893 | L22: 4855 | M22: 2162 | N22: 3664
B23: Plant Machinery | C23: 158 | D23: 99 | E23: 105 | F23: 116 | G23: 119 | H23: 134 | I23: 158 | J23: 168 | K23: 221 | L23: 287 | M23: 437 | N23: 825
B24: Equipments | C24: 10 | D24: 9 | E24: 11 | F24: 14 | G24: 16 | H24: 23 | I24: 29 | J24: 30 | K24: 33 | L24: 39 | M24: 44 | N24: 56
B25: Computers | C25: 50 | D25: 38 | E25: 38 | F25: 40 | G25: 42 | H25: 49 | I25: 58 | J25: 59 | K25: 70 | L25: 98 | M25: 112 | N25: 175
B26: Furniture n fittings | C26: 160 | D26: 122 | E26: 132 | F26: 138 | G26: 145 | H26: 164 | I26: 183 | J26: 192 | K26: 225 | L26: 328 | M26: 486 | N26: 758
B27: Vehicles | C27: 1 | D27: 1 | E27: 1 | F27: 1 | G27: 1 | H27: 1 | I27: 3 | J27: 3 | K27: 3 | L27: 3 | M27: 3 | N27: 4
B28: Intangible Assets | C28: 81 | D28: 26 | E28: 26 | F28: 26 | G28: 55 | H28: 55 | I28: 62 | J28: 62 | K28: 62 | L28: 62 | M28: 62 | N28: 62
B29: Other fixed assets | C29: 150 | D29: 322 | E29: 18 | F29: 56 | G29: 63 | H29: 66 | I29: 69 | J29: 70 | K29: 78 | L29: 92 | M29: 92 | N29: 98
B30: Gross Block | C30: 946 | D30: 951 | E30: 680 | F30: 775 | G30: 860 | H30: 938 | I30: 3246 | J30: 3764 | K30: 5647 | L30: 5840 | M30: 3485 | N30: 5730
B31: Accumulated Depreciation | C31: 226 | D31: 282 | E31: 203 | F31: 227 | G31: 248 | H31: 276 | I31: 508 | J31: 711 | K31: 961 | L31: 1314 | M31: 1035 | N31: 1835
B32: Net Block | C32: =C30-C31 -> 720 | D32: =D30-D31 -> 669 | E32: =E30-E31 -> 477 | F32: =F30-F31 -> 548 | G32: =G30-G31 -> 612 | H32: =H30-H31 -> 662 | I32: =I30-I31 -> 2738 | J32: =J30-J31 -> 3053 | ... N32: =N30-N31 -> 3895
B34: CWIP | C34: 138 | D34: 92 | E34: 55 | F34: 5 | G34: 10 | H34: 87 | I34: 23 | J34: 108 | K34: 105 | L34: 102 | M34: 224 | N34: 180
B35: Investments | C35: 300 | D35: 740 | E35: 1067 | F35: 1080 | G35: 1023 | H35: 883 | I35: 1515 | J35: 1487 | K35: 1284 | L35: 1110 | M35: 1416 | N35: 1480
B37: Other Assets -
B38: Inventories | C38: 356 | D38: 330 | E38: 279 | F38: 305 | G38: 345 | H38: 497 | I38: 608 | J38: 428 | K38: 868 | L38: 1361 | M38: 1583 | N38: 2045
B39: Trade receivables | C39: 18 | D39: 18 | E39: 13 | F39: 6 | G39: 15 | H39: 17 | I39: 17 | J39: 21 | K39: 18 | L39: 34 | M39: 82 | N39: 63
B40: Cash Equivalents | C40: 62 | D40: 56 | E40: 27 | F40: 34 | G40: 33 | H40: 54 | I40: 61 | J40: 81 | K40: 86 | L40: 86 | M40: 298 | N40: 340
B41: Loans n Advances | C41: 59 | D41: 31 | E41: 16 | F41: 9 | G41: 12 | H41: 26 | I41: 102 | J41: 25 | K41: 29 | L41: 29 | M41: 35 | N41: 17
B42: Other asset items | C42: 283 | D42: 272 | E42: 223 | F42: 233 | G42: 286 | H42: 332 | I42: 442 | J42: 519 | K42: 650 | L42: 832 | M42: 1075 | N42: 1400
B43: Total Assets | C43: 1936 | D43: 2207 | E43: 2157 | F43: 2222 | G43: 2336 | H43: 2559 | I43: 5507 | J43: 5724 | K43: 7726 | L43: 8082 | M43: 7162 | N43: 9420
B45: Particulars | C45: 41699 | D45: 42064 | E45: 42430 | F45: 42795 | G45: 43160 | H45: 43525 | I45: 43891 | J45: 44256 | K45: 44621 | L45: 44986 | M45: 45352 | N45: 45717
B46: Cash from Operating Activity - | C46: -46 | D46: -10 | E46: 109 | F46: 102 | G46: 77 | H46: 21 | I46: 361 | J46: 285 | K46: 58 | L46: 595 | M46: 1349 | N46: 1661
B47: Profit from operations | C47: 32 | D47: 65 | E47: 98 | F47: 165 | G47: 191 | H47: 233 | I47: 542 | J47: 180 | K47: 569 | L47: 1079 | M47: 1919 | N47: 2723
B48: Receivables | C48: -8 | D48: -19 | E48: -1 | F48: 24 | G48: -54 | H48: -11 | I48: -20 | J48: -39 | K48: -103 | L48: -101 | M48: -208 | N48: -203
B49: Inventory | C49: -25 | D49: -3 | E49: -19 | F49: -26 | G49: -39 | H49: -152 | I49: -89 | J49: 179 | K49: -439 | L49: -494 | M49: -222 | N49: -462
B50: Payables | C50: -14 | D50: -6 | E50: 27 | F50: -9 | G50: 43 | H50: 49 | I50: 26 | J50: -11 | K50: 134 | L50: 332 | M50: 178 | N50: 212
... B75: Net Cash Flow | C75: -145 | D75: -6 | E75: -2 | F75: 7 | G75: -1 | H75: 21 | I75: 5 | J75: 20 | K75: 6 | L75: 1 | M75: 211 | N75: 44

Sheet Intrinsic growth
B5: Calculation of ROIC | G5: ='Raw FS'!J5 -> 44256 | H5: ='Raw FS'!K5 -> 44621 | I5: ='Raw FS'!L5 -> 44986 | J5: ='Raw FS'!M5 -> 45352 | K5: ='Raw FS'!N5 -> 45717
B7: Current Assets
B8: ='Raw FS'!B38 -> Inventories | G8: ='Raw FS'!J38 -> 428 | H8: ='Raw FS'!K38 -> 868 | I8: ='Raw FS'!L38 -> 1361 | J8: ='Raw FS'!M38 -> 1583 | K8: ='Raw FS'!N38 -> 2045
B9: ='Raw FS'!B39 -> Trade receivables | G9: ='Raw FS'!J39 -> 21 | H9: ='Raw FS'!K39 -> 18 | I9: ='Raw FS'!L39 -> 34 | J9: ='Raw FS'!M39 -> 82 | K9: ='Raw FS'!N39 -> 63
B10: ='Raw FS'!B41 -> Loans n Advances | G10: ='Raw FS'!J41 -> 25 | H10: ='Raw FS'!K41 -> 29 | I10: ='Raw FS'!L41 -> 29 | J10: ='Raw FS'!M41 -> 35 | K10: ='Raw FS'!N41 -> 17
B11: ='Raw FS'!B42 -> Other asset items | G11: ='Raw FS'!J42 -> 519 | H11: ='Raw FS'!K42 -> 650 | I11: ='Raw FS'!L42 -> 832 | J11: ='Raw FS'!M42 -> 1075 | K11: ='Raw FS'!N42 -> 1400
B12: Total Current Assets | G12: =SUM(G8:G11) -> 993 | H12: =SUM(H8:H11) -> 1565 | I12: =SUM(I8:I11) -> 2256 | J12: =SUM(J8:J11) -> 2775 | K12: =SUM(K8:K11) -> 3525
B14: Current Liabilities
B15: ='Raw FS'!B16 -> Trade Payables | G15: ='Raw FS'!J16 -> 275 | H15: ='Raw FS'!K16 -> 378 | I15: ='Raw FS'!L16 -> 665 | J15: ='Raw FS'!M16 -> 774 | K15: ='Raw FS'!N16 -> 928
B16: ='Raw FS'!B17 -> Other liability items | G16: ='Raw FS'!J17 -> 2792 | H16: ='Raw FS'!K17 -> 213 | I16: ='Raw FS'!L17 -> 289 | J16: ='Raw FS'!M17 -> 532 | K16: ='Raw FS'!N17 -> 671
B17: Total Current Liabilities | G17: =SUM(G15:G16) -> 3067 | H17: =SUM(H15:H16) -> 591 | I17: =SUM(I15:I16) -> 954 | J17: =SUM(J15:J16) -> 1306 | K17: =SUM(K15:K16) -> 1599
A19: # | B19: Net Working Capital | G19: =G12-G17 -> -2074 | H19: =H12-H17 -> 974 | I19: =I12-I17 -> 1302 | J19: =J12-J17 -> 1469 | K19: =K12-K17 -> 1926
B21: Non-Current Assets
B22: ='Raw FS'!B21 -> Land | G22: ='Raw FS'!J21 -> 63 | H22: ='Raw FS'!K21 -> 62 | I22: ='Raw FS'!L21 -> 77 | J22: ='Raw FS'!M21 -> 86 | K22: ='Raw FS'!N21 -> 86
B23: ='Raw FS'!B22 -> Building | G23: ='Raw FS'!J22 -> 3117 | H23: ='Raw FS'!K22 -> 4893 | I23: ='Raw FS'!L22 -> 4855 | J23: ='Raw FS'!M22 -> 2162 | K23: ='Raw FS'!N22 -> 3664
B24: ='Raw FS'!B23 -> Plant Machinery | G24: ='Raw FS'!J23 -> 168 | H24: ='Raw FS'!K23 -> 221 | I24: ='Raw FS'!L23 -> 287 | J24: ='Raw FS'!M23 -> 437 | K24: ='Raw FS'!N23 -> 825
B25: ='Raw FS'!B24 -> Equipments | G25: ='Raw FS'!J24 -> 30 | H25: ='Raw FS'!K24 -> 33 | I25: ='Raw FS'!L24 -> 39 | J25: ='Raw FS'!M24 -> 44 | K25: ='Raw FS'!N24 -> 56
B26: ='Raw FS'!B25 -> Computers | G26: ='Raw FS'!J25 -> 59 | H26: ='Raw FS'!K25 -> 70 | I26: ='Raw FS'!L25 -> 98 | J26: ='Raw FS'!M25 -> 112 | K26: ='Raw FS'!N25 -> 175
B27: ='Raw FS'!B26 -> Furniture n fittings | G27: ='Raw FS'!J26 -> 192 | H27: ='Raw FS'!K26 -> 225 | I27: ='Raw FS'!L26 -> 328 | J27: ='Raw FS'!M26 -> 486 | K27: ='Raw FS'!N26 -> 758
B28: ='Raw FS'!B27 -> Vehicles | G28: ='Raw FS'!J27 -> 3 | H28: ='Raw FS'!K27 -> 3 | I28: ='Raw FS'!L27 -> 3 | J28: ='Raw FS'!M27 -> 3 | K28: ='Raw FS'!N27 -> 4
B29: ='Raw FS'!B28 -> Intangible Assets | G29: ='Raw FS'!J28 -> 62 | H29: ='Raw FS'!K28 -> 62 | I29: ='Raw FS'!L28 -> 62 | J29: ='Raw FS'!M28 -> 62 | K29: ='Raw FS'!N28 -> 62
B30: ='Raw FS'!B29 -> Other fixed assets | G30: ='Raw FS'!J29 -> 70 | H30: ='Raw FS'!K29 -> 78 | I30: ='Raw FS'!L29 -> 92 | J30: ='Raw FS'!M29 -> 92 | K30: ='Raw FS'!N29 -> 98
B32: Gross Block | G32: =SUM(G22:G31) -> 3764 | H32: =SUM(H22:H31) -> 5647 | I32: =SUM(I22:I31) -> 5841 | J32: =SUM(J22:J31) -> 3484 | K32: =SUM(K22:K31) -> 5728
B33: ='Raw FS'!B31 -> Accumulated Depreciation | G33: =-'Raw FS'!J31 -> -711 | H33: =-'Raw FS'!K31 -> -961 | I33: =-'Raw FS'!L31 -> -1314 | J33: =-'Raw FS'!M31 -> -1035 | K33: =-'Raw FS'!N31 -> -1835
A34: # | B34: Net Non- Current Assets | G34: =SUM(G32:G33) -> 3053 | H34: =SUM(H32:H33) -> 4686 | I34: =SUM(I32:I33) -> 4527 | J34: =SUM(J32:J33) -> 2449 | K34: =SUM(K32:K33) -> 3893
A36: # | B36: Invested Capital | G36: =SUM(G34,G12) -> 4046 | H36: =SUM(H34,H12) -> 6251 | I36: =SUM(I34,I12) -> 6783 | J36: =SUM(J34,J12) -> 5224 | K36: =SUM(K34,K12) -> 7418
B37: EBIT | G37: =DCF!C39 -> -143.43 | H37: =DCF!D39 -> 283.9 | I37: =DCF!E39 -> 620.46 | J37: =DCF!F39 -> 1299.58 | K37: =DCF!G39 -> 1924.78
A39: # | B39: ROIC | G39: =G37/G36 -> -0.035449827 | H39: =H37/H36 -> 0.045416733 | I39: =I37/I36 -> 0.0914728 | J39: =J37/J36 -> 0.24877106 | K39: =K37/K36 -> 0.25947425
B41: Calculation of Reinvestment Rate | G41: =G5 -> 44256 | H41: =H5 -> 44621 | I41: =I5 -> 44986 | J41: =J5 -> 45352 | K41: =K5 -> 45717
B43: Net Capex | G43: =-SUM('Raw FS'!J56:J57) -> 91 | H43: =-SUM('Raw FS'!K56:K57) -> 210 | I43: =-SUM('Raw FS'!L56:L57) -> 223 | J43: =-SUM('Raw FS'!M56:M57) -> 394 | K43: =-SUM('Raw FS'!N56:N57) -> 861
B44: Change in Working Capital | H44: =H19-G19 -> 3048 | I44: =I19-H19 -> 328 | J44: =J19-I19 -> 167 | K44: =K19-J19 -> 457
B46: EBIT | G46: =G37 -> -143.43 | H46: =H37 -> 283.9 | I46: =I37 -> 620.46 | J46: =J37 -> 1299.58 | K46: =K37 -> 1924.78
B47: Marginal Tax rate | G47: 0.25 | H47: =G47 -> 0.25 | I47: =H47 -> 0.25 | J47: =I47 -> 0.25 | K47: =J47 -> 0.25
B48: EBIT(1-tax ) | G48: =G46*(1-Tax_rate) -> -107.5725 | H48: =H46*(1-Tax_rate) -> 212.925 | I48: =I46*(1-Tax_rate) -> 465.345 | J48: =J46*(1-Tax_rate) -> 974.685 | K48: =K46*(1-Tax_rate) -> 1443.585
B50: Reinvestment | G50: ` | H50: =SUM(H43:H44) -> 3258 | I50: =SUM(I43:I44) -> 551 | J50: =SUM(J43:J44) -> 561 | K50: =SUM(K43:K44) -> 1318
B52: Reinvestment Rate | H52: =H50/H48 -> 15.301162 | I52: =I50/I48 -> 1.1840677 | J52: =J50/J48 -> 0.57557057 | K52: =K50/K48 -> 0.91300478
J54: 4 Year Average | K54: =AVERAGE(H52:K52) -> 4.4934514
J55: 4 Year Median | K55: =MEDIAN(H52:K52) -> 1.0485363
B57: Calculation of Growth Rate | G57: =G41 -> 44256 | H57: =H41 -> 44621 | I57: =I41 -> 44986 | J57: =J41 -> 45352 | K57: =K41 -> 45717
B59: Reinvestment Rate | H59: =H52 -> 15.301162 | I59: =I52 -> 1.1840677 | J59: =J52 -> 0.57557057 | K59: =K52 -> 0.91300478
B60: ROIC | H60: =H39 -> 0.045416733 | I60: =I39 -> 0.0914728 | J60: =J39 -> 0.24877106 | K60: =K39 -> 0.25947425
B62: Intrinsic Growth | H62: =H59*H60 -> 0.69492881 | I62: =I59*I60 -> 0.10830999 | J62: =J59*J60 -> 0.1431853 | K62: =K59*K60 -> 0.23690123
J64: 4 Year Average | K64: =AVERAGE(H62:K62) -> 0.29583133
J65: 4 Year Median | K65: =MEDIAN(H62:K62) -> 0.19004326

Sheet Trent- Beta Regression
B5: Regression Beta-2 Years weekly
B7: Avenue Supermarket Weekly Returns | F7: NIFTY Returns | I7: Beta Drifting
B9: Date | C9: Closing Price | D9: Return | F9: Closing Price | G9: Return | I9: Levered Raw Beta | J9: =M10 -> -0.3533564
B10: 25-01-2026 | C10: 3721.3 | F10: 25320.65 | I10: Beta Weight | J10: 0.75 | L10: Beta 1 | M10: =SLOPE(D11:D113,G11:G113) -> -0.3533564
B11: 18-01-2026 | C11: 3785.5 | D11: =(C11/C10)-1 -> 0.017252036 | F11: 25048.65 | G11: =(F11/F10)-1 -> -0.01074222 | L11: Beta 2 | M11: =_xlfn.COVARIANCE.S(D10:D113,G10:G113)/_xlfn.VAR.S(G10:G113) -> -0.3533564
B12: 46327 | C12: 3755.9 | D12: =(C12/C11)-1 -> -0.0078193105 | F12: 25694.35 | G12: =(F12/F11)-1 -> 0.025777836 | I12: Market Beta | J12: 1
B13: 46113 | C13: 3899.7 | D13: =(C13/C12)-1 -> 0.038286429 | F13: 25683.3 | G13: =(F13/F12)-1 -> -0.00043005563 | I13: Market Beta weight | J13: 0.25 | L13: Beta 3 | M13: =M32 -> -0.3533564
B14: 28-12-2025 | C14: 3972.9 | D14: =(C14/C13)-1 -> 0.018770675 | F14: 26328.55 | G14: =(F14/F13)-1 -> 0.025123329
B15: 21-12-2025 | C15: 4409.6 | D15: =(C15/C14)-1 -> 0.10991971 | F15: 26042.3 | G15: =(F15/F14)-1 -> -0.010872228 | I15: Adjusted Beta | J15: =(J9*J10)+(J12*J13) -> -0.015017297 | L15: SUMMARY OUTPUT
B16: 14-12-2025 | C16: 4285.3 | D16: =(C16/C15)-1 -> -0.028188498 | F16: 25966.4 | G16: =(F16/F15)-1 -> -0.0029144891
B17: 45850 | C17: 4062.2 | D17: =(C17/C16)-1 -> -0.052061699 | F17: 26046.95 | G17: =(F17/F16)-1 -> 0.0031020858 | L17: Regression Statistics
B18: 30-11-2025 | C18: 4075.4 | D18: =(C18/C17)-1 -> 0.0032494707 | F18: 26186.45 | G18: =(F18/F17)-1 -> 0.0053557134 | L18: Multiple R | M18: 0.11875998
B19: 23-11-2025 | C19: 4183.1 | D19: =(C19/C18)-1 -> 0.026426854 | F19: 26202.95 | G19: =(F19/F18)-1 -> 0.00063009686 | L19: R Square | M19: 0.014103933
B20: 16-11-2025 | C20: 4250.4 | D20: =(C20/C19)-1 -> 0.016088547 | F20: 26068.15 | G20: =(F20/F19)-1 -> -0.0051444589 | L20: Adjusted R Square | M20: 0.004342586
B21: 45911 | C21: 4359.1 | D21: =(C21/C20)-1 -> 0.025574064 | F21: 25910.05 | G21: =(F21/F20)-1 -> -0.0060648723 | L21: Standard Error | M21: 0.05000331
B22: 45699 | C22: 4391.2 | D22: =(C22/C21)-1 -> 0.0073639054 | F22: 25492.3 | G22: =(F22/F21)-1 -> -0.016123087 | L22: Observations | M22: 103
B23: 26-10-2025 | C23: 4627.3 | D23: =(C23/C22)-1 -> 0.053766624 | F23: 25722.1 | G23: =(F23/F22)-1 -> 0.0090144867
B24: 19-10-2025 | C24: 4694.3 | D24: =(C24/C23)-1 -> 0.014479286 | F24: 25795.15 | G24: =(F24/F23)-1 -> 0.0028399703 | L24: ANOVA
B25: 46001 | C25: 4789.6 | D25: =(C25/C24)-1 -> 0.020301216 | F25: 25709.85 | G25: =(F25/F24)-1 -> -0.0033068232 | M25: df | N25: SS | O25: MS | P25: F | Q25: Significance F
B26: 45787 | C26: 4814.4 | D26: =(C26/C25)-1 -> 0.0051778854 | F26: 25285.35 | G26: =(F26/F25)-1 -> -0.016511182 | L26: Regression | M26: 1 | N26: 0.0036126675 | O26: 0.0036126675 | P26: 1.4448757 | Q26: 0.23216271
B27: 28-09-2025 | C27: 4691.1 | D27: =(C27/C26)-1 -> -0.025610668 | F27: 24894.25 | G27: =(F27/F26)-1 -> -0.015467454 | L27: Residual | M27: 101 | N27: 0.25253343 | O27: 0.002500331
B28: 21-09-2025 | C28: 4815.7 | D28: =(C28/C27)-1 -> 0.026560935 | F28: 24654.7 | G28: =(F28/F27)-1 -> -0.009622704 | L28: Total | M28: 102 | N28: 0.2561461
B29: 14-09-2025 | C29: 4679 | D29: =(C29/C28)-1 -> -0.02838632 | F29: 25327.05 | G29: =(F29/F28)-1 -> 0.027270662
B30: 45847 | C30: 5080 | D30: =(C30/C29)-1 -> 0.085702073 | F30: 25114 | G30: =(F30/F29)-1 -> -0.0084119548 | M30: Coefficients | N30: Standard Error | O30: t Stat | P30: P-value | Q30: Lower 95% | R30: Upper 95% | S30: Lower 95.0% | T30: Upper 95.0%
B31: 31-08-2025 | C31: 5130 | D31: =(C31/C30)-1 -> 0.0098425197 | F31: 24741 | G31: =(F31/F30)-1 -> -0.014852274 | L31: Intercept | M31: 0.0015107526 | N31: 0.0049422328 | O31: 0.3056822 | P31: 0.76047577 | Q31: -0.0082933079 | R31: 0.011314813 | S31: -0.0082933079 | T31: 0.011314813
B32: 24-08-2025 | C32: 5528.5 | D32: =(C32/C31)-1 -> 0.077680312 | F32: 24426.85 | G32: =(F32/F31)-1 -> -0.012697547 | L32: X Variable 1 | M32: -0.3533564 | N32: 0.29396641 | O32: -1.2020298 | P32: 0.23216271 | Q32: -0.93650669 | R32: 0.22979389 | S32: -0.93650669 | T32: 0.22979389
B33: 17-08-2025 | C33: 5298 | D33: =(C33/C32)-1 -> -0.041693045 | F33: 24870.1 | G33: =(F33/F32)-1 -> 0.018146016
B34: 45938 | C34: 5418 | D34: =(C34/C33)-1 -> 0.022650057 | F34: 24631.3 | G34: =(F34/F33)-1 -> -0.0096018914
B35: 45724 | C35: 5370.5 | D35: =(C35/C34)-1 -> -0.0087670727 | F35: 24363.3 | G35: =(F35/F34)-1 -> -0.010880465
B36: 27-07-2025 | C36: 5317 | D36: =(C36/C35)-1 -> -0.0099618285 | F36: 24565.35 | G36: =(F36/F35)-1 -> 0.0082932115
B37: 20-07-2025 | C37: 5180 | D37: =(C37/C36)-1 -> -0.02576641 | F37: 24837 | G37: =(F37/F36)-1 -> 0.011058259
B38: 13-07-2025 | C38: 5043 | D38: =(C38/C37)-1 -> -0.026447876 | F38: 24968.4 | G38: =(F38/F37)-1 -> 0.005290494
B39: 45815 | C39: 5375 | D39: =(C39/C38)-1 -> 0.065833829 | F39: 25149.85 | G39: =(F39/F38)-1 -> 0.0072671857
B40: 29-06-2025 | C40: 5364 | D40: =(C40/C39)-1 -> -0.0020465116 | F40: 25461 | G40: =(F40/F39)-1 -> 0.012371843
B41: 22-06-2025 | C41: 5456 | D41: =(C41/C40)-1 -> 0.01715138 | F41: 25637.8 | G41: =(F41/F40)-1 -> 0.0069439535
B42: 15-06-2025 | C42: 6019.5 | D42: =(C42/C41)-1 -> 0.10328079 | F42: 25112.4 | G42: =(F42/F41)-1 -> -0.020493178
B43: 45875 | C43: 5897.5 | D43: =(C43/C42)-1 -> -0.020267464 | F43: 24718.6 | G43: =(F43/F42)-1 -> -0.015681496
B44: 45663 | C44: 5590 | D44: =(C44/C43)-1 -> -0.052140738 | F44: 25003.05 | G44: =(F44/F43)-1 -> 0.011507529
B45: 25-05-2025 | C45: 5777 | D45: =(C45/C44)-1 -> 0.033452594 | F45: 24750.7 | G45: =(F45/F44)-1 -> -0.010092769
B46: 18-05-2025 | C46: 5643.5 | D46: =(C46/C45)-1 -> -0.02310888 | F46: 24853.15 | G46: =(F46/F45)-1 -> 0.0041392769
B47: 45966 | C47: 5435.5 | D47: =(C47/C46)-1 -> -0.036856561 | F47: 25019.8 | G47: =(F47/F46)-1 -> 0.0067053874
B48: 45752 | C48: 5583 | D48: =(C48/C47)-1 -> 0.027136418 | F48: 24008 | G48: =(F48/F47)-1 -> -0.040439972
B49: 27-04-2025 | C49: 5113 | D49: =(C49/C48)-1 -> -0.08418413 | F49: 24346.7 | G49: =(F49/F48)-1 -> 0.014107797
B50: 20-04-2025 | C50: 5148 | D50: =(C50/C49)-1 -> 0.0068452963 | F50: 24039.35 | G50: =(F50/F49)-1 -> -0.012623887
B51: 13-04-2025 | C51: 5145 | D51: =(C51/C50)-1 -> -0.00058275058 | F51: 23851.65 | G51: =(F51/F50)-1 -> -0.0078080314
B52: 45812 | C52: 5130.5 | D52: =(C52/C51)-1 -> -0.0028182702 | F52: 22828.55 | G52: =(F52/F51)-1 -> -0.042894307
B53: 30-03-2025 | C53: 4780.55 | D53: =(C53/C52)-1 -> -0.068209726 | F53: 22904.45 | G53: =(F53/F52)-1 -> 0.0033247841
B54: 23-03-2025 | C54: 5562.85 | D54: =(C54/C53)-1 -> 0.16364226 | F54: 23519.35 | G54: =(F54/F53)-1 -> 0.026846312
B55: 16-03-2025 | C55: 5325.15 | D55: =(C55/C54)-1 -> -0.042729896 | F55: 23350.4 | G55: =(F55/F54)-1 -> -0.0071834468
B56: 45903 | C56: 5150.05 | D56: =(C56/C55)-1 -> -0.032881703 | F56: 22397.2 | G56: =(F56/F55)-1 -> -0.040821571
B57: 45691 | C57: 5022.4 | D57: =(C57/C56)-1 -> -0.024786167 | F57: 22552.5 | G57: =(F57/F56)-1 -> 0.0069339025
B58: 23-02-2025 | C58: 4999.85 | D58: =(C58/C57)-1 -> -0.0044898853 | F58: 22124.7 | G58: =(F58/F57)-1 -> -0.018969072
B59: 16-02-2025 | C59: 4851.55 | D59: =(C59/C58)-1 -> -0.02966089 | F59: 22795.9 | G59: =(F59/F58)-1 -> 0.030337135
B60: 45902 | C60: 5048.2 | D60: =(C60/C59)-1 -> 0.040533438 | F60: 22929.25 | G60: =(F60/F59)-1 -> 0.0058497361
B61: 45690 | C61: 5117.35 | D61: =(C61/C60)-1 -> 0.013697952 | F61: 23559.95 | G61: =(F61/F60)-1 -> 0.027506351
B62: 26-01-2025 | C62: 5454.4 | D62: =(C62/C61)-1 -> 0.065864168 | F62: 23508.4 | G62: =(F62/F61)-1 -> -0.0021880352
B63: 19-01-2025 | C63: 5753.2 | D63: =(C63/C62)-1 -> 0.054781461 | F63: 23092.2 | G63: =(F63/F62)-1 -> -0.01770431
B64: 45992 | C64: 5490.45 | D64: =(C64/C63)-1 -> -0.045670236 | F64: 23203.2 | G64: =(F64/F63)-1 -> 0.0048068179
B65: 45778 | C65: 6216.55 | D65: =(C65/C64)-1 -> 0.13224781 | F65: 23431.5 | G65: =(F65/F64)-1 -> 0.0098391601
B66: 29-12-2024 | C66: 6584.1 | D66: =(C66/C65)-1 -> 0.059124434 | F66: 24004.75 | G66: =(F66/F65)-1 -> 0.02446493
B67: 22-12-2024 | C67: 7307.7 | D67: =(C67/C66)-1 -> 0.10990113 | F67: 23813.4 | G67: =(F67/F66)-1 -> -0.007971339
B68: 15-12-2024 | C68: 7118.3 | D68: =(C68/C67)-1 -> -0.025917867 | F68: 23587.5 | G68: =(F68/F67)-1 -> -0.0094862556
B69: 45516 | C69: 6831.55 | D69: =(C69/C68)-1 -> -0.040283495 | F69: 24768.3 | G69: =(F69/F68)-1 -> 0.050060413
B70: 45303 | C70: 7000.25 | D70: =(C70/C69)-1 -> 0.024694249 | F70: 24677.8 | G70: =(F70/F69)-1 -> -0.003653864
B71: 24-11-2024 | C71: 6999.95 | D71: =(C71/C70)-1 -> -4.2855612e-05 | F71: 24131.1 | G71: =(F71/F70)-1 -> -0.022153514
B72: 17-11-2024 | C72: 6795.4 | D72: =(C72/C71)-1 -> -0.029221637 | F72: 23907.25 | G72: =(F72/F71)-1 -> -0.0092764109
B73: 45576 | C73: 6652.8 | D73: =(C73/C72)-1 -> -0.020984784 | F73: 23532.7 | G73: =(F73/F72)-1 -> -0.015666796
B74: 45362 | C74: 6463 | D74: =(C74/C73)-1 -> -0.028529341 | F74: 24148.2 | G74: =(F74/F73)-1 -> 0.026155095
B75: 27-10-2024 | C75: 6298.95 | D75: =(C75/C74)-1 -> -0.025382949 | F75: 24304.35 | G75: =(F75/F74)-1 -> 0.0064663205
B76: 20-10-2024 | C76: 7149 | D76: =(C76/C75)-1 -> 0.13495106 | F76: 24180.8 | G76: =(F76/F75)-1 -> -0.0050834521
B77: 13-10-2024 | C77: 7361.45 | D77: =(C77/C76)-1 -> 0.029717443 | F77: 24854.05 | G77: =(F77/F76)-1 -> 0.027842338
B78: 45453 | C78: 7768.05 | D78: =(C78/C77)-1 -> 0.055233684 | F78: 24964.25 | G78: =(F78/F77)-1 -> 0.004433885
B79: 29-09-2024 | C79: 8234.95 | D79: =(C79/C78)-1 -> 0.060105174 | F79: 25014.6 | G79: =(F79/F78)-1 -> 0.0020168841
B80: 22-09-2024 | C80: 7353.3 | D80: =(C80/C79)-1 -> -0.10706197 | F80: 26178.95 | G80: =(F80/F79)-1 -> 0.046546817
B81: 15-09-2024 | C81: 7833.7 | D81: =(C81/C80)-1 -> 0.065331212 | F81: 25790.95 | G81: =(F81/F80)-1 -> -0.014821068
B82: 45513 | C82: 7465.15 | D82: =(C82/C81)-1 -> -0.047046734 | F82: 25356.5 | G82: =(F82/F81)-1 -> -0.016845056
B83: 45300 | C83: 7233.15 | D83: =(C83/C82)-1 -> -0.031077741 | F83: 24852.15 | G83: =(F83/F82)-1 -> -0.019890363
B84: 25-08-2024 | C84: 7103.55 | D84: =(C84/C83)-1 -> -0.017917505 | F84: 25235.9 | G84: =(F84/F83)-1 -> 0.01544132
B85: 18-08-2024 | C85: 7158.75 | D85: =(C85/C84)-1 -> 0.0077707625 | F85: 24823.15 | G85: =(F85/F84)-1 -> -0.016355668
B86: 45604 | C86: 6948.75 | D86: =(C86/C85)-1 -> -0.02933473 | F86: 24541.15 | G86: =(F86/F85)-1 -> -0.011360363
B87: 45390 | C87: 6502.4 | D87: =(C87/C86)-1 -> -0.064234575 | F87: 24367.5 | G87: =(F87/F86)-1 -> -0.0070758705
B88: 28-07-2024 | C88: 6275.35 | D88: =(C88/C87)-1 -> -0.034917876 | F88: 24717.7 | G88: =(F88/F87)-1 -> 0.014371602
B89: 21-07-2024 | C89: 5538.25 | D89: =(C89/C88)-1 -> -0.11745958 | F89: 24834.85 | G89: =(F89/F88)-1 -> 0.0047395186
B90: 14-07-2024 | C90: 5393.35 | D90: =(C90/C89)-1 -> -0.026163499 | F90: 24530.9 | G90: =(F90/F89)-1 -> -0.01223885
B91: 45480 | C91: 5166.35 | D91: =(C91/C90)-1 -> -0.042088869 | F91: 24502.15 | G91: =(F91/F90)-1 -> -0.0011719912
B92: 30-06-2024 | C92: 5651.25 | D92: =(C92/C91)-1 -> 0.093857365 | F92: 24323.85 | G92: =(F92/F91)-1 -> -0.0072769124
B93: 23-06-2024 | C93: 5619.9 | D93: =(C93/C92)-1 -> -0.0055474453 | F93: 24010.6 | G93: =(F93/F92)-1 -> -0.012878307
B94: 16-06-2024 | C94: 5479.85 | D94: =(C94/C93)-1 -> -0.024920372 | F94: 23501.1 | G94: =(F94/F93)-1 -> -0.021219795
B95: 45541 | C95: 5266.35 | D95: =(C95/C94)-1 -> -0.03896092 | F95: 23465.6 | G95: =(F95/F94)-1 -> -0.0015105676
B96: 45328 | C96: 5245.55 | D96: =(C96/C95)-1 -> -0.0039496046 | F96: 23290.15 | G96: =(F96/F95)-1 -> -0.0074769024
B97: 26-05-2024 | C97: 4964.6 | D97: =(C97/C96)-1 -> -0.053559684 | F97: 22530.7 | G97: =(F97/F96)-1 -> -0.032608206
B98: 19-05-2024 | C98: 4559.15 | D98: =(C98/C97)-1 -> -0.081668211 | F98: 22957.1 | G98: =(F98/F97)-1 -> 0.018925289
B99: 45631 | C99: 4715.4 | D99: =(C99/C98)-1 -> 0.034271739 | F99: 22466.1 | G99: =(F99/F98)-1 -> -0.021387719
B100: 45417 | C100: 4634.55 | D100: =(C100/C99)-1 -> -0.017145947 | F100: 22055.2 | G100: =(F100/F99)-1 -> -0.018289779
B101: 28-04-2024 | C101: 4471.4 | D101: =(C101/C100)-1 -> -0.035202986 | F101: 22475.85 | G101: =(F101/F100)-1 -> 0.0190726
B102: 21-04-2024 | C102: 4523.65 | D102: =(C102/C101)-1 -> 0.011685378 | F102: 22419.95 | G102: =(F102/F101)-1 -> -0.0024871139
B103: 14-04-2024 | C103: 4304.85 | D103: =(C103/C102)-1 -> -0.048368021 | F103: 22147 | G103: =(F103/F102)-1 -> -0.012174425
B104: 45477 | C104: 4158.95 | D104: =(C104/C103)-1 -> -0.033892006 | F104: 22519.4 | G104: =(F104/F103)-1 -> 0.016814918
B105: 31-03-2024 | C105: 4053.85 | D105: =(C105/C104)-1 -> -0.025270802 | F105: 22513.7 | G105: =(F105/F104)-1 -> -0.00025311509
B106: 24-03-2024 | C106: 3932.6 | D106: =(C106/C105)-1 -> -0.029909839 | F106: 22326.9 | G106: =(F106/F105)-1 -> -0.0082971702
...

Sheet DMART- Beta Regression
B5: Regression Beta-2 Years weekly
B7: Avenue Supermarket Weekly Returns | F7: NIFTY Returns | I7: Beta Drifting
B9: Date | C9: Closing Price | D9: Return | F9: Closing Price | G9: Return | I9: Levered Raw Beta | J9: =M10 -> 0.9679798
B10: 25-01-2026 | C10: 3689.5 | F10: 25320.65 | I10: Beta Weight | J10: 0.75 | L10: Beta 1 | M10: =SLOPE(D11:D113,G11:G113) -> 0.9679798
B11: 18-01-2026 | C11: 3665.6 | D11: =(C11/C10)-1 -> -0.0064778425 | F11: 25048.65 | G11: =(F11/F10)-1 -> -0.01074222 | L11: Beta 2 | M11: =_xlfn.COVARIANCE.S(D10:D113,G10:G113)/_xlfn.VAR.S(G10:G113) -> 0.9679798
B12: 46327 | C12: 3775.7 | D12: =(C12/C11)-1 -> 0.03003601 | F12: 25694.35 | G12: =(F12/F11)-1 -> 0.025777836 | I12: Market Beta | J12: 1
B13: 46113 | C13: 3801.3 | D13: =(C13/C12)-1 -> 0.0067801997 | F13: 25683.3 | G13: =(F13/F12)-1 -> -0.00043005563 | I13: Market Beta weight | J13: 0.25 | L13: Beta 3 | M13: =M32 -> 0.9679798
B14: 28-12-2025 | C14: 3719.8 | D14: =(C14/C13)-1 -> -0.021440034 | F14: 26328.55 | G14: =(F14/F13)-1 -> 0.025123329
B15: 21-12-2025 | C15: 3787.4 | D15: =(C15/C14)-1 -> 0.01817302 | F15: 26042.3 | G15: =(F15/F14)-1 -> -0.010872228 | I15: Adjusted Beta | J15: =(J9*J10)+(J12*J13) -> 0.97598485 | L15: SUMMARY OUTPUT
B16: 14-12-2025 | C16: 3819.5 | D16: =(C16/C15)-1 -> 0.0084754713 | F16: 25966.4 | G16: =(F16/F15)-1 -> -0.0029144891
B17: 45850 | C17: 3843 | D17: =(C17/C16)-1 -> 0.0061526378 | F17: 26046.95 | G17: =(F17/F16)-1 -> 0.0031020858 | L17: Regression Statistics
B18: 30-11-2025 | C18: 3952.1 | D18: =(C18/C17)-1 -> 0.028389279 | F18: 26186.45 | G18: =(F18/F17)-1 -> 0.0053557134 | L18: Multiple R | M18: 0.40026591
B19: 23-11-2025 | C19: 3996.5 | D19: =(C19/C18)-1 -> 0.011234534 | F19: 26202.95 | G19: =(F19/F18)-1 -> 0.00063009686 | L19: R Square | M19: 0.1602128
B20: 16-11-2025 | C20: 4038 | D20: =(C20/C19)-1 -> 0.010384086 | F20: 26068.15 | G20: =(F20/F19)-1 -> -0.0051444589 | L20: Adjusted R Square | M20: 0.15189808
B21: 45911 | C21: 4053.7 | D21: =(C21/C20)-1 -> 0.0038880634 | F21: 25910.05 | G21: =(F21/F20)-1 -> -0.0060648723 | L21: Standard Error | M21: 0.03750962
B22: 45699 | C22: 4011 | D22: =(C22/C21)-1 -> -0.010533587 | F22: 25492.3 | G22: =(F22/F21)-1 -> -0.016123087 | L22: Observations | M22: 103
B23: 26-10-2025 | C23: 4153.5 | D23: =(C23/C22)-1 -> 0.0355273 | F23: 25722.1 | G23: =(F23/F22)-1 -> 0.0090144867
B24: 19-10-2025 | C24: 4213.9 | D24: =(C24/C23)-1 -> 0.014541953 | F24: 25795.15 | G24: =(F24/F23)-1 -> 0.0028399703 | L24: ANOVA
B25: 46001 | C25: 4302.5 | D25: =(C25/C24)-1 -> 0.021025653 | F25: 25709.85 | G25: =(F25/F24)-1 -> -0.0033068232 | M25: df | N25: SS | O25: MS | P25: F | Q25: Significance F
B26: 45787 | C26: 4320.4 | D26: =(C26/C25)-1 -> 0.0041603719 | F26: 25285.35 | G26: =(F26/F25)-1 -> -0.016511182 | L26: Regression | M26: 1 | N26: 0.027110321 | O26: 0.027110321 | P26: 19.268564 | Q26: 2.799294e-05
B27: 28-09-2025 | C27: 4418.4 | D27: =(C27/C26)-1 -> 0.022683085 | F27: 24894.25 | G27: =(F27/F26)-1 -> -0.015467454 | L27: Residual | M27: 101 | N27: 0.14210413 | O27: 0.0014069716
B28: 21-09-2025 | C28: 4517.8 | D28: =(C28/C27)-1 -> 0.022496831 | F28: 24654.7 | G28: =(F28/F27)-1 -> -0.009622704 | L28: Total | M28: 102 | N28: 0.16921445
B29: 14-09-2025 | C29: 4775.3 | D29: =(C29/C28)-1 -> 0.056996768 | F29: 25327.05 | G29: =(F29/F28)-1 -> 0.027270662
B30: 45847 | C30: 4616.6 | D30: =(C30/C29)-1 -> -0.033233514 | F30: 25114 | G30: =(F30/F29)-1 -> -0.0084119548 | M30: Coefficients | N30: Standard Error | O30: t Stat | P30: P-value | Q30: Lower 95% | R30: Upper 95% | S30: Lower 95.0% | T30: Upper 95.0%
B31: 31-08-2025 | C31: 4793.3 | D31: =(C31/C30)-1 -> 0.038274921 | F31: 24741 | G31: =(F31/F30)-1 -> -0.014852274 | L31: Intercept | M31: 0.0021740691 | N31: 0.0037073801 | O31: 0.58641658 | P31: 0.55890396 | Q31: -0.0051803756 | R31: 0.0095285139 | S31: -0.0051803756 | T31: 0.0095285139
B32: 24-08-2025 | C32: 4755.6 | D32: =(C32/C31)-1 -> -0.0078651451 | F32: 24426.85 | G32: =(F32/F31)-1 -> -0.012697547 | L32: X Variable 1 | M32: 0.9679798 | N32: 0.22051677 | O32: 4.3895972 | P32: 2.799294e-05 | Q32: 0.53053384 | R32: 1.4054258 | S32: 0.53053384 | T32: 1.4054258
B33: 17-08-2025 | C33: 4698.8 | D33: =(C33/C32)-1 -> -0.011943814 | F33: 24870.1 | G33: =(F33/F32)-1 -> 0.018146016
B34: 45938 | C34: 4358.2 | D34: =(C34/C33)-1 -> -0.072486592 | F34: 24631.3 | G34: =(F34/F33)-1 -> -0.0096018914
B35: 45724 | C35: 4170.1 | D35: =(C35/C34)-1 -> -0.04316002 | F35: 24363.3 | G35: =(F35/F34)-1 -> -0.010880465
B36: 27-07-2025 | C36: 4196 | D36: =(C36/C35)-1 -> 0.0062108822 | F36: 24565.35 | G36: =(F36/F35)-1 -> 0.0082932115
B37: 20-07-2025 | C37: 3997 | D37: =(C37/C36)-1 -> -0.04742612 | F37: 24837 | G37: =(F37/F36)-1 -> 0.011058259
B38: 13-07-2025 | C38: 4048.6 | D38: =(C38/C37)-1 -> 0.012909682 | F38: 24968.4 | G38: =(F38/F37)-1 -> 0.005290494
B39: 45815 | C39: 4064.2 | D39: =(C39/C38)-1 -> 0.0038531838 | F39: 25149.85 | G39: =(F39/F38)-1 -> 0.0072671857
B40: 29-06-2025 | C40: 4261.1 | D40: =(C40/C39)-1 -> 0.048447419 | F40: 25461 | G40: =(F40/F39)-1 -> 0.012371843
B41: 22-06-2025 | C41: 4313.5 | D41: =(C41/C40)-1 -> 0.012297294 | F41: 25637.8 | G41: =(F41/F40)-1 -> 0.0069439535
B42: 15-06-2025 | C42: 4300.3 | D42: =(C42/C41)-1 -> -0.00306016 | F42: 25112.4 | G42: =(F42/F41)-1 -> -0.020493178
B43: 45875 | C43: 4051.9 | D43: =(C43/C42)-1 -> -0.057763412 | F43: 24718.6 | G43: =(F43/F42)-1 -> -0.015681496
B44: 45663 | C44: 4201.6 | D44: =(C44/C43)-1 -> 0.03694563 | F44: 25003.05 | G44: =(F44/F43)-1 -> 0.011507529
B45: 25-05-2025 | C45: 4002.1 | D45: =(C45/C44)-1 -> -0.047481912 | F45: 24750.7 | G45: =(F45/F44)-1 -> -0.010092769
B46: 18-05-2025 | C46: 4140.8 | D46: =(C46/C45)-1 -> 0.034656805 | F46: 24853.15 | G46: =(F46/F45)-1 -> 0.0041392769
B47: 45966 | C47: 4189.7 | D47: =(C47/C46)-1 -> 0.011809312 | F47: 25019.8 | G47: =(F47/F46)-1 -> 0.0067053874
B48: 45752 | C48: 3972.4 | D48: =(C48/C47)-1 -> -0.051865289 | F48: 24008 | G48: =(F48/F47)-1 -> -0.040439972
B49: 27-04-2025 | C49: 4059.2 | D49: =(C49/C48)-1 -> 0.02185077 | F49: 24346.7 | G49: =(F49/F48)-1 -> 0.014107797
B50: 20-04-2025 | C50: 4375.2 | D50: =(C50/C49)-1 -> 0.077847852 | F50: 24039.35 | G50: =(F50/F49)-1 -> -0.012623887
B51: 13-04-2025 | C51: 4357.1 | D51: =(C51/C50)-1 -> -0.0041369537 | F51: 23851.65 | G51: =(F51/F50)-1 -> -0.0078080314
B52: 45812 | C52: 4131.5 | D52: =(C52/C51)-1 -> -0.051777558 | F52: 22828.55 | G52: =(F52/F51)-1 -> -0.042894307
B53: 30-03-2025 | C53: 4039.9 | D53: =(C53/C52)-1 -> -0.022171124 | F53: 22904.45 | G53: =(F53/F52)-1 -> 0.0033247841
B54: 23-03-2025 | C54: 4083.2 | D54: =(C54/C53)-1 -> 0.010718087 | F54: 23519.35 | G54: =(F54/F53)-1 -> 0.026846312
B55: 16-03-2025 | C55: 3892.2 | D55: =(C55/C54)-1 -> -0.046777038 | F55: 23350.4 | G55: =(F55/F54)-1 -> -0.0071834468
B56: 45903 | C56: 3797.1 | D56: =(C56/C55)-1 -> -0.024433482 | F56: 22397.2 | G56: =(F56/F55)-1 -> -0.040821571
B57: 45691 | C57: 3593.6 | D57: =(C57/C56)-1 -> -0.053593532 | F57: 22552.5 | G57: =(F57/F56)-1 -> 0.0069339025
B58: 23-02-2025 | C58: 3403.95 | D58: =(C58/C57)-1 -> -0.052774377 | F58: 22124.7 | G58: =(F58/F57)-1 -> -0.018969072
B59: 16-02-2025 | C59: 3596.7 | D59: =(C59/C58)-1 -> 0.056625391 | F59: 22795.9 | G59: =(F59/F58)-1 -> 0.030337135
B60: 45902 | C60: 3682.65 | D60: =(C60/C59)-1 -> 0.023896905 | F60: 22929.25 | G60: =(F60/F59)-1 -> 0.0058497361
B61: 45690 | C61: 3743.5 | D61: =(C61/C60)-1 -> 0.016523427 | F61: 23559.95 | G61: =(F61/F60)-1 -> 0.027506351
B62: 26-01-2025 | C62: 3664.65 | D62: =(C62/C61)-1 -> -0.021063176 | F62: 23508.4 | G62: =(F62/F61)-1 -> -0.0021880352
B63: 19-01-2025 | C63: 3579.95 | D63: =(C63/C62)-1 -> -0.023112712 | F63: 23092.2 | G63: =(F63/F62)-1 -> -0.01770431
B64: 45992 | C64: 3620.65 | D64: =(C64/C63)-1 -> 0.011368874 | F64: 23203.2 | G64: =(F64/F63)-1 -> 0.0048068179
B65: 45778 | C65: 3686.25 | D65: =(C65/C64)-1 -> 0.018118294 | F65: 23431.5 | G65: =(F65/F64)-1 -> 0.0098391601
B66: 29-12-2024 | C66: 4025.2 | D66: =(C66/C65)-1 -> 0.091949813 | F66: 24004.75 | G66: =(F66/F65)-1 -> 0.02446493
B67: 22-12-2024 | C67: 3568.35 | D67: =(C67/C66)-1 -> -0.11349747 | F67: 23813.4 | G67: =(F67/F66)-1 -> -0.007971339
B68: 15-12-2024 | C68: 3408.3 | D68: =(C68/C67)-1 -> -0.044852663 | F68: 23587.5 | G68: =(F68/F67)-1 -> -0.0094862556
B69: 45516 | C69: 3652.3 | D69: =(C69/C68)-1 -> 0.071589942 | F69: 24768.3 | G69: =(F69/F68)-1 -> 0.050060413
B70: 45303 | C70: 3805.55 | D70: =(C70/C69)-1 -> 0.041959861 | F70: 24677.8 | G70: =(F70/F69)-1 -> -0.003653864
B71: 24-11-2024 | C71: 3709.6 | D71: =(C71/C70)-1 -> -0.025213175 | F71: 24131.1 | G71: =(F71/F70)-1 -> -0.022153514
B72: 17-11-2024 | C72: 3613.65 | D72: =(C72/C71)-1 -> -0.025865322 | F72: 23907.25 | G72: =(F72/F71)-1 -> -0.0092764109
B73: 45576 | C73: 3823.85 | D73: =(C73/C72)-1 -> 0.058168334 | F73: 23532.7 | G73: =(F73/F72)-1 -> -0.015666796
B74: 45362 | C74: 3874.5 | D74: =(C74/C73)-1 -> 0.013245812 | F74: 24148.2 | G74: =(F74/F73)-1 -> 0.026155095
B75: 27-10-2024 | C75: 4001.6 | D75: =(C75/C74)-1 -> 0.032804233 | F75: 24304.35 | G75: =(F75/F74)-1 -> 0.0064663205
B76: 20-10-2024 | C76: 4052.2 | D76: =(C76/C75)-1 -> 0.012644942 | F76: 24180.8 | G76: =(F76/F75)-1 -> -0.0050834521
B77: 13-10-2024 | C77: 3986.7 | D77: =(C77/C76)-1 -> -0.016164059 | F77: 24854.05 | G77: =(F77/F76)-1 -> 0.027842338
B78: 45453 | C78: 4572.7 | D78: =(C78/C77)-1 -> 0.14698874 | F78: 24964.25 | G78: =(F78/F77)-1 -> 0.004433885
B79: 29-09-2024 | C79: 4737.55 | D79: =(C79/C78)-1 -> 0.036050911 | F79: 25014.6 | G79: =(F79/F78)-1 -> 0.0020168841
B80: 22-09-2024 | C80: 5102.3 | D80: =(C80/C79)-1 -> 0.076991272 | F80: 26178.95 | G80: =(F80/F79)-1 -> 0.046546817
B81: 15-09-2024 | C81: 5320.55 | D81: =(C81/C80)-1 -> 0.042774827 | F81: 25790.95 | G81: =(F81/F80)-1 -> -0.014821068
B82: 45513 | C82: 5187.05 | D82: =(C82/C81)-1 -> -0.025091391 | F82: 25356.5 | G82: =(F82/F81)-1 -> -0.016845056
B83: 45300 | C83: 5303.45 | D83: =(C83/C82)-1 -> 0.022440501 | F83: 24852.15 | G83: =(F83/F82)-1 -> -0.019890363
B84: 25-08-2024 | C84: 4927.45 | D84: =(C84/C83)-1 -> -0.070897246 | F84: 25235.9 | G84: =(F84/F83)-1 -> 0.01544132
B85: 18-08-2024 | C85: 4901.5 | D85: =(C85/C84)-1 -> -0.0052664157 | F85: 24823.15 | G85: =(F85/F84)-1 -> -0.016355668
B86: 45604 | C86: 5021.3 | D86: =(C86/C85)-1 -> 0.024441498 | F86: 24541.15 | G86: =(F86/F85)-1 -> -0.011360363
B87: 45390 | C87: 4989.95 | D87: =(C87/C86)-1 -> -0.0062434031 | F87: 24367.5 | G87: =(F87/F86)-1 -> -0.0070758705
B88: 28-07-2024 | C88: 4909.7 | D88: =(C88/C87)-1 -> -0.016082325 | F88: 24717.7 | G88: =(F88/F87)-1 -> 0.014371602
B89: 21-07-2024 | C89: 5071.6 | D89: =(C89/C88)-1 -> 0.032975538 | F89: 24834.85 | G89: =(F89/F88)-1 -> 0.0047395186
B90: 14-07-2024 | C90: 5010.7 | D90: =(C90/C89)-1 -> -0.012008045 | F90: 24530.9 | G90: =(F90/F89)-1 -> -0.01223885
B91: 45480 | C91: 4943.65 | D91: =(C91/C90)-1 -> -0.013381364 | F91: 24502.15 | G91: =(F91/F90)-1 -> -0.0011719912
B92: 30-06-2024 | C92: 4853.1 | D92: =(C92/C91)-1 -> -0.018316426 | F92: 24323.85 | G92: =(F92/F91)-1 -> -0.0072769124
B93: 23-06-2024 | C93: 4716.75 | D93: =(C93/C92)-1 -> -0.028095444 | F93: 24010.6 | G93: =(F93/F92)-1 -> -0.012878307
B94: 16-06-2024 | C94: 4804.85 | D94: =(C94/C93)-1 -> 0.018678115 | F94: 23501.1 | G94: =(F94/F93)-1 -> -0.021219795
B95: 45541 | C95: 4739.95 | D95: =(C95/C94)-1 -> -0.013507185 | F95: 23465.6 | G95: =(F95/F94)-1 -> -0.0015105676
B96: 45328 | C96: 4747.25 | D96: =(C96/C95)-1 -> 0.0015401006 | F96: 23290.15 | G96: =(F96/F95)-1 -> -0.0074769024
B97: 26-05-2024 | C97: 4302.15 | D97: =(C97/C96)-1 -> -0.093759545 | F97: 22530.7 | G97: =(F97/F96)-1 -> -0.032608206
B98: 19-05-2024 | C98: 4684.5 | D98: =(C98/C97)-1 -> 0.088874168 | F98: 22957.1 | G98: =(F98/F97)-1 -> 0.018925289
B99: 45631 | C99: 4682.9 | D99: =(C99/C98)-1 -> -0.00034155193 | F99: 22466.1 | G99: =(F99/F98)-1 -> -0.021387719
B100: 45417 | C100: 4796.8 | D100: =(C100/C99)-1 -> 0.024322535 | F100: 22055.2 | G100: =(F100/F99)-1 -> -0.018289779
B101: 28-04-2024 | C101: 4612.35 | D101: =(C101/C100)-1 -> -0.038452718 | F101: 22475.85 | G101: =(F101/F100)-1 -> 0.0190726
B102: 21-04-2024 | C102: 4553.15 | D102: =(C102/C101)-1 -> -0.012835106 | F102: 22419.95 | G102: =(F102/F101)-1 -> -0.0024871139
B103: 14-04-2024 | C103: 4696 | D103: =(C103/C102)-1 -> 0.031373884 | F103: 22147 | G103: =(F103/F102)-1 -> -0.012174425
B104: 45477 | C104: 4765.05 | D104: =(C104/C103)-1 -> 0.014704003 | F104: 22519.4 | G104: =(F104/F103)-1 -> 0.016814918
B105: 31-03-2024 | C105: 4619.25 | D105: =(C105/C104)-1 -> -0.03059779 | F105: 22513.7 | G105: =(F105/F104)-1 -> -0.00025311509
B106: 24-03-2024 | C106: 4525.6 | D106: =(C106/C105)-1 -> -0.020273854 | F106: 22326.9 | G106: =(F106/F105)-1 -> -0.0082971702
...

Sheet VMM - Beta Regression 
B5: Regression Beta-2 Years weekly
B7: Avenue Supermarket Weekly Returns | F7: NIFTY Returns | I7: Beta Drifting
B9: Date | C9: Closing Price | D9: Return | F9: Closing Price | G9: Return | I9: Levered Raw Beta | J9: =M10 -> 1.2186694
B10: 25-01-2026 | C10: 125.95 | F10: 25320.65 | I10: Beta Weight | J10: 0.75 | L10: Beta 1 | M10: =SLOPE(D11:D113,G11:G113) -> 1.2186694
B11: 18-01-2026 | C11: 124.58 | D11: =(C11/C10)-1 -> -0.010877332 | F11: 25048.65 | G11: =(F11/F10)-1 -> -0.01074222 | L11: Beta 2 | M11: =_xlfn.COVARIANCE.S(D10:D113,G10:G113)/_xlfn.VAR.S(G10:G113) -> 1.2186694
B12: 46327 | C12: 129.54 | D12: =(C12/C11)-1 -> 0.039813774 | F12: 25694.35 | G12: =(F12/F11)-1 -> 0.025777836 | I12: Market Beta | J12: 1
B13: 46113 | C13: 129.19 | D13: =(C13/C12)-1 -> -0.0027018681 | F13: 25683.3 | G13: =(F13/F12)-1 -> -0.00043005563 | I13: Market Beta weight | J13: 0.25 | L13: Beta 3 | M13: =M32 -> 1.2186694
B14: 28-12-2025 | C14: 135.95 | D14: =(C14/C13)-1 -> 0.052326031 | F14: 26328.55 | G14: =(F14/F13)-1 -> 0.025123329
B15: 21-12-2025 | C15: 136.26 | D15: =(C15/C14)-1 -> 0.0022802501 | F15: 26042.3 | G15: =(F15/F14)-1 -> -0.010872228 | I15: Adjusted Beta | J15: =(J9*J10)+(J12*J13) -> 1.164002 | L15: SUMMARY OUTPUT
B16: 14-12-2025 | C16: 138.07 | D16: =(C16/C15)-1 -> 0.013283429 | F16: 25966.4 | G16: =(F16/F15)-1 -> -0.0029144891
B17: 45850 | C17: 134.77 | D17: =(C17/C16)-1 -> -0.02390092 | F17: 26046.95 | G17: =(F17/F16)-1 -> 0.0031020858 | L17: Regression Statistics
B18: 30-11-2025 | C18: 133.03 | D18: =(C18/C17)-1 -> -0.012910885 | F18: 26186.45 | G18: =(F18/F17)-1 -> 0.0053557134 | L18: Multiple R | M18: 0.54981223
B19: 23-11-2025 | C19: 135.8 | D19: =(C19/C18)-1 -> 0.020822371 | F19: 26202.95 | G19: =(F19/F18)-1 -> 0.00063009686 | L19: R Square | M19: 0.30229349
B20: 16-11-2025 | C20: 130.92 | D20: =(C20/C19)-1 -> -0.035935199 | F20: 26068.15 | G20: =(F20/F19)-1 -> -0.0051444589 | L20: Adjusted R Square | M20: 0.28960792
B21: 45911 | C21: 136.94 | D21: =(C21/C20)-1 -> 0.045982279 | F21: 25910.05 | G21: =(F21/F20)-1 -> -0.0060648723 | L21: Standard Error | M21: 0.03086888
B22: 45699 | C22: 143.18 | D22: =(C22/C21)-1 -> 0.045567402 | F22: 25492.3 | G22: =(F22/F21)-1 -> -0.016123087 | L22: Observations | M22: 57
B23: 26-10-2025 | C23: 144.69 | D23: =(C23/C22)-1 -> 0.010546166 | F23: 25722.1 | G23: =(F23/F22)-1 -> 0.0090144867
B24: 19-10-2025 | C24: 148.29 | D24: =(C24/C23)-1 -> 0.02488078 | F24: 25795.15 | G24: =(F24/F23)-1 -> 0.0028399703 | L24: ANOVA
B25: 46001 | C25: 148.43 | D25: =(C25/C24)-1 -> 0.00094409603 | F25: 25709.85 | G25: =(F25/F24)-1 -> -0.0033068232 | M25: df | N25: SS | O25: MS | P25: F | Q25: Significance F
B26: 45787 | C26: 146.2 | D26: =(C26/C25)-1 -> -0.015023917 | F26: 25285.35 | G26: =(F26/F25)-1 -> -0.016511182 | L26: Regression | M26: 1 | N26: 0.022707036 | O26: 0.022707036 | P26: 23.829707 | Q26: 9.4284518e-06
B27: 28-09-2025 | C27: 149.99 | D27: =(C27/C26)-1 -> 0.025923393 | F27: 24894.25 | G27: =(F27/F26)-1 -> -0.015467454 | L27: Residual | M27: 55 | N27: 0.052408827 | O27: 0.00095288776
B28: 21-09-2025 | C28: 143.95 | D28: =(C28/C27)-1 -> -0.040269351 | F28: 24654.7 | G28: =(F28/F27)-1 -> -0.009622704 | L28: Total | M28: 56 | N28: 0.075115863
B29: 14-09-2025 | C29: 152.35 | D29: =(C29/C28)-1 -> 0.058353595 | F29: 25327.05 | G29: =(F29/F28)-1 -> 0.027270662
B30: 45847 | C30: 152.59 | D30: =(C30/C29)-1 -> 0.00157532 | F30: 25114 | G30: =(F30/F29)-1 -> -0.0084119548 | M30: Coefficients | N30: Standard Error | O30: t Stat | P30: P-value | Q30: Lower 95% | R30: Upper 95% | S30: Lower 95.0% | T30: Upper 95.0%
B31: 31-08-2025 | C31: 152.48 | D31: =(C31/C30)-1 -> -0.00072088603 | F31: 24741 | G31: =(F31/F30)-1 -> -0.014852274 | L31: Intercept | M31: -0.0011869367 | N31: 0.0040954322 | O31: -0.28981963 | P31: 0.77304406 | Q31: -0.0093943661 | R31: 0.0070204928 | S31: -0.0093943661 | T31: 0.0070204928
B32: 24-08-2025 | C32: 149.41 | D32: =(C32/C31)-1 -> -0.020133788 | F32: 24426.85 | G32: =(F32/F31)-1 -> -0.012697547 | L32: X Variable 1 | M32: 1.2186694 | N32: 0.24964712 | O32: 4.8815681 | P32: 9.4284518e-06 | Q32: 0.7183654 | R32: 1.7189734 | S32: 0.7183654 | T32: 1.7189734
B33: 17-08-2025 | C33: 150.67 | D33: =(C33/C32)-1 -> 0.0084331705 | F33: 24870.1 | G33: =(F33/F32)-1 -> 0.018146016
B34: 45938 | C34: 146.56 | D34: =(C34/C33)-1 -> -0.027278158 | F34: 24631.3 | G34: =(F34/F33)-1 -> -0.0096018914
B35: 45724 | C35: 139.01 | D35: =(C35/C34)-1 -> -0.051514738 | F35: 24363.3 | G35: =(F35/F34)-1 -> -0.010880465
B36: 27-07-2025 | C36: 141.07 | D36: =(C36/C35)-1 -> 0.014819078 | F36: 24565.35 | G36: =(F36/F35)-1 -> 0.0082932115
B37: 20-07-2025 | C37: 139.93 | D37: =(C37/C36)-1 -> -0.0080810945 | F37: 24837 | G37: =(F37/F36)-1 -> 0.011058259
B38: 13-07-2025 | C38: 138.07 | D38: =(C38/C37)-1 -> -0.01329236 | F38: 24968.4 | G38: =(F38/F37)-1 -> 0.005290494
B39: 45815 | C39: 133.62 | D39: =(C39/C38)-1 -> -0.032230028 | F39: 25149.85 | G39: =(F39/F38)-1 -> 0.0072671857
B40: 29-06-2025 | C40: 129.35 | D40: =(C40/C39)-1 -> -0.031956294 | F40: 25461 | G40: =(F40/F39)-1 -> 0.012371843
B41: 22-06-2025 | C41: 134.66 | D41: =(C41/C40)-1 -> 0.041051411 | F41: 25637.8 | G41: =(F41/F40)-1 -> 0.0069439535
B42: 15-06-2025 | C42: 129.62 | D42: =(C42/C41)-1 -> -0.037427595 | F42: 25112.4 | G42: =(F42/F41)-1 -> -0.020493178
B43: 45875 | C43: 123.69 | D43: =(C43/C42)-1 -> -0.045749113 | F43: 24718.6 | G43: =(F43/F42)-1 -> -0.015681496
B44: 45663 | C44: 127.23 | D44: =(C44/C43)-1 -> 0.028619937 | F44: 25003.05 | G44: =(F44/F43)-1 -> 0.011507529
B45: 25-05-2025 | C45: 124.66 | D45: =(C45/C44)-1 -> -0.020199638 | F45: 24750.7 | G45: =(F45/F44)-1 -> -0.010092769
B46: 18-05-2025 | C46: 122.72 | D46: =(C46/C45)-1 -> -0.01556233 | F46: 24853.15 | G46: =(F46/F45)-1 -> 0.0041392769
B47: 45966 | C47: 126.27 | D47: =(C47/C46)-1 -> 0.02892764 | F47: 25019.8 | G47: =(F47/F46)-1 -> 0.0067053874
B48: 45752 | C48: 120.79 | D48: =(C48/C47)-1 -> -0.043399065 | F48: 24008 | G48: =(F48/F47)-1 -> -0.040439972
B49: 27-04-2025 | C49: 121.31 | D49: =(C49/C48)-1 -> 0.0043049921 | F49: 24346.7 | G49: =(F49/F48)-1 -> 0.014107797
B50: 20-04-2025 | C50: 107.32 | D50: =(C50/C49)-1 -> -0.11532438 | F50: 24039.35 | G50: =(F50/F49)-1 -> -0.012623887
B51: 13-04-2025 | C51: 108.67 | D51: =(C51/C50)-1 -> 0.012579202 | F51: 23851.65 | G51: =(F51/F50)-1 -> -0.0078080314
B52: 45812 | C52: 104.51 | D52: =(C52/C51)-1 -> -0.038281034 | F52: 22828.55 | G52: =(F52/F51)-1 -> -0.042894307
B53: 30-03-2025 | C53: 105.79 | D53: =(C53/C52)-1 -> 0.012247632 | F53: 22904.45 | G53: =(F53/F52)-1 -> 0.0033247841
B54: 23-03-2025 | C54: 104.24 | D54: =(C54/C53)-1 -> -0.014651668 | F54: 23519.35 | G54: =(F54/F53)-1 -> 0.026846312
B55: 16-03-2025 | C55: 102.1 | D55: =(C55/C54)-1 -> -0.020529547 | F55: 23350.4 | G55: =(F55/F54)-1 -> -0.0071834468
B56: 45903 | C56: 99.44 | D56: =(C56/C55)-1 -> -0.026052889 | F56: 22397.2 | G56: =(F56/F55)-1 -> -0.040821571
B57: 45691 | C57: 104.57 | D57: =(C57/C56)-1 -> 0.051588898 | F57: 22552.5 | G57: =(F57/F56)-1 -> 0.0069339025
B58: 23-02-2025 | C58: 100.21 | D58: =(C58/C57)-1 -> -0.041694559 | F58: 22124.7 | G58: =(F58/F57)-1 -> -0.018969072
B59: 16-02-2025 | C59: 102.65 | D59: =(C59/C58)-1 -> 0.024348867 | F59: 22795.9 | G59: =(F59/F58)-1 -> 0.030337135
B60: 45902 | C60: 104.54 | D60: =(C60/C59)-1 -> 0.01841208 | F60: 22929.25 | G60: =(F60/F59)-1 -> 0.0058497361
B61: 45690 | C61: 113.13 | D61: =(C61/C60)-1 -> 0.082169504 | F61: 23559.95 | G61: =(F61/F60)-1 -> 0.027506351
B62: 26-01-2025 | C62: 107.95 | D62: =(C62/C61)-1 -> -0.045788031 | F62: 23508.4 | G62: =(F62/F61)-1 -> -0.0021880352
B63: 19-01-2025 | C63: 102.81 | D63: =(C63/C62)-1 -> -0.047614636 | F63: 23092.2 | G63: =(F63/F62)-1 -> -0.01770431
B64: 45992 | C64: 109.84 | D64: =(C64/C63)-1 -> 0.068378562 | F64: 23203.2 | G64: =(F64/F63)-1 -> 0.0048068179
B65: 45778 | C65: 108.51 | D65: =(C65/C64)-1 -> -0.012108521 | F65: 23431.5 | G65: =(F65/F64)-1 -> 0.0098391601
B66: 29-12-2024 | C66: 112.18 | D66: =(C66/C65)-1 -> 0.033821768 | F66: 24004.75 | G66: =(F66/F65)-1 -> 0.02446493
B67: 22-12-2024 | C67: 106.14 | D67: =(C67/C66)-1 -> -0.05384204 | F67: 23813.4 | G67: =(F67/F66)-1 -> -0.007971339

Sheet ABLBL- Beta Regression
B5: Regression Beta-2 Years weekly
B7: Avenue Supermarket Weekly Returns | F7: NIFTY Returns | I7: Beta Drifting
B9: Date | C9: Closing Price | D9: Return | F9: Closing Price | G9: Return | I9: Levered Raw Beta | J9: =M10 -> 1.6753739
B10: 25-01-2026 | C10: 66.41 | F10: 25320.65 | I10: Beta Weight | J10: 0.75 | L10: Beta 1 | M10: =SLOPE(D11:D113,G11:G113) -> 1.6753739
B11: 18-01-2026 | C11: 61.64 | D11: =(C11/C10)-1 -> -0.071826532 | F11: 25048.65 | G11: =(F11/F10)-1 -> -0.01074222 | L11: Beta 2 | M11: =_xlfn.COVARIANCE.S(D10:D113,G10:G113)/_xlfn.VAR.S(G10:G113) -> 1.6753739
B12: 46327 | C12: 71.3 | D12: =(C12/C11)-1 -> 0.15671642 | F12: 25694.35 | G12: =(F12/F11)-1 -> 0.025777836 | I12: Market Beta | J12: 1
B13: 46113 | C13: 74.54 | D13: =(C13/C12)-1 -> 0.045441795 | F13: 25683.3 | G13: =(F13/F12)-1 -> -0.00043005563 | I13: Market Beta weight | J13: 0.25 | L13: Beta 3 | M13: =M32 -> 1.6753739
B14: 28-12-2025 | C14: 78.16 | D14: =(C14/C13)-1 -> 0.048564529 | F14: 26328.55 | G14: =(F14/F13)-1 -> 0.025123329
B15: 21-12-2025 | C15: 76.78 | D15: =(C15/C14)-1 -> -0.01765609 | F15: 26042.3 | G15: =(F15/F14)-1 -> -0.010872228 | I15: Adjusted Beta | J15: =(J9*J10)+(J12*J13) -> 1.5065304 | L15: SUMMARY OUTPUT
B16: 14-12-2025 | C16: 76.82 | D16: =(C16/C15)-1 -> 0.000520969 | F16: 25966.4 | G16: =(F16/F15)-1 -> -0.0029144891
B17: 45850 | C17: 77.67 | D17: =(C17/C16)-1 -> 0.011064827 | F17: 26046.95 | G17: =(F17/F16)-1 -> 0.0031020858 | L17: Regression Statistics
B18: 30-11-2025 | C18: 77.41 | D18: =(C18/C17)-1 -> -0.0033474958 | F18: 26186.45 | G18: =(F18/F17)-1 -> 0.0053557134 | L18: Multiple R | M18: 0.55134824
B19: 23-11-2025 | C19: 78.15 | D19: =(C19/C18)-1 -> 0.0095594884 | F19: 26202.95 | G19: =(F19/F18)-1 -> 0.00063009686 | L19: R Square | M19: 0.30398488
B20: 16-11-2025 | C20: 76.71 | D20: =(C20/C19)-1 -> -0.018426104 | F20: 26068.15 | G20: =(F20/F19)-1 -> -0.0051444589 | L20: Adjusted R Square | M20: 0.29709365
B21: 45911 | C21: 78.44 | D21: =(C21/C20)-1 -> 0.02255247 | F21: 25910.05 | G21: =(F21/F20)-1 -> -0.0060648723 | L21: Standard Error | M21: 0.042907719
B22: 45699 | C22: 79.7 | D22: =(C22/C21)-1 -> 0.016063233 | F22: 25492.3 | G22: =(F22/F21)-1 -> -0.016123087 | L22: Observations | M22: 103
B23: 26-10-2025 | C23: 81.64 | D23: =(C23/C22)-1 -> 0.02434128 | F23: 25722.1 | G23: =(F23/F22)-1 -> 0.0090144867
B24: 19-10-2025 | C24: 81.93 | D24: =(C24/C23)-1 -> 0.0035521803 | F24: 25795.15 | G24: =(F24/F23)-1 -> 0.0028399703 | L24: ANOVA
B25: 46001 | C25: 82.28 | D25: =(C25/C24)-1 -> 0.0042719395 | F25: 25709.85 | G25: =(F25/F24)-1 -> -0.0033068232 | M25: df | N25: SS | O25: MS | P25: F | Q25: Significance F
B26: 45787 | C26: 83.19 | D26: =(C26/C25)-1 -> 0.011059796 | F26: 25285.35 | G26: =(F26/F25)-1 -> -0.016511182 | L26: Regression | M26: 1 | N26: 0.081212999 | O26: 0.081212999 | P26: 44.111791 | Q26: 1.5861465e-09
B27: 28-09-2025 | C27: 87.99 | D27: =(C27/C26)-1 -> 0.057699243 | F27: 24894.25 | G27: =(F27/F26)-1 -> -0.015467454 | L27: Residual | M27: 101 | N27: 0.18594831 | O27: 0.0018410724
B28: 21-09-2025 | C28: 84.9 | D28: =(C28/C27)-1 -> -0.035117627 | F28: 24654.7 | G28: =(F28/F27)-1 -> -0.009622704 | L28: Total | M28: 102 | N28: 0.26716131
B29: 14-09-2025 | C29: 92.11 | D29: =(C29/C28)-1 -> 0.084923439 | F29: 25327.05 | G29: =(F29/F28)-1 -> 0.027270662
B30: 45847 | C30: 88.38 | D30: =(C30/C29)-1 -> -0.04049506 | F30: 25114 | G30: =(F30/F29)-1 -> -0.0084119548 | M30: Coefficients | N30: Standard Error | O30: t Stat | P30: P-value | Q30: Lower 95% | R30: Upper 95% | S30: Lower 95.0% | T30: Upper 95.0%
B31: 31-08-2025 | C31: 85.92 | D31: =(C31/C30)-1 -> -0.027834352 | F31: 24741 | G31: =(F31/F30)-1 -> -0.014852274 | L31: Intercept | M31: 0.0066927346 | N31: 0.004240918 | O31: 1.5781335 | P31: 0.11766196 | Q31: -0.0017201059 | R31: 0.015105575 | S31: -0.0017201059 | T31: 0.015105575
B32: 24-08-2025 | C32: 77.35 | D32: =(C32/C31)-1 -> -0.099743948 | F32: 24426.85 | G32: =(F32/F31)-1 -> -0.012697547 | L32: X Variable 1 | M32: 1.6753739 | N32: 0.25225187 | O32: 6.6416708 | P32: 1.5861465e-09 | Q32: 1.174974 | R32: 2.1757737 | S32: 1.174974 | T32: 2.1757737
B33: 17-08-2025 | C33: 81.25 | D33: =(C33/C32)-1 -> 0.050420168 | F33: 24870.1 | G33: =(F33/F32)-1 -> 0.018146016
B34: 45938 | C34: 75 | D34: =(C34/C33)-1 -> -0.076923077 | F34: 24631.3 | G34: =(F34/F33)-1 -> -0.0096018914
B35: 45724 | C35: 74.19 | D35: =(C35/C34)-1 -> -0.0108 | F35: 24363.3 | G35: =(F35/F34)-1 -> -0.010880465
B36: 27-07-2025 | C36: 73.78 | D36: =(C36/C35)-1 -> -0.0055263513 | F36: 24565.35 | G36: =(F36/F35)-1 -> 0.0082932115
B37: 20-07-2025 | C37: 73.77 | D37: =(C37/C36)-1 -> -0.00013553809 | F37: 24837 | G37: =(F37/F36)-1 -> 0.011058259
B38: 13-07-2025 | C38: 75.51 | D38: =(C38/C37)-1 -> 0.023586824 | F38: 24968.4 | G38: =(F38/F37)-1 -> 0.005290494
B39: 45815 | C39: 76.85 | D39: =(C39/C38)-1 -> 0.017745994 | F39: 25149.85 | G39: =(F39/F38)-1 -> 0.0072671857
B40: 29-06-2025 | C40: 78.33 | D40: =(C40/C39)-1 -> 0.019258295 | F40: 25461 | G40: =(F40/F39)-1 -> 0.012371843
B41: 22-06-2025 | C41: 74.7 | D41: =(C41/C40)-1 -> -0.046342398 | F41: 25637.8 | G41: =(F41/F40)-1 -> 0.0069439535
B42: 15-06-2025 | C42: 73.66 | D42: =(C42/C41)-1 -> -0.013922356 | F42: 25112.4 | G42: =(F42/F41)-1 -> -0.020493178
B43: 45875 | C43: 73.8 | D43: =(C43/C42)-1 -> 0.0019006245 | F43: 24718.6 | G43: =(F43/F42)-1 -> -0.015681496
B44: 45663 | C44: 77.77 | D44: =(C44/C43)-1 -> 0.053794038 | F44: 25003.05 | G44: =(F44/F43)-1 -> 0.011507529
B45: 25-05-2025 | C45: 85.85 | D45: =(C45/C44)-1 -> 0.1038961 | F45: 24750.7 | G45: =(F45/F44)-1 -> -0.010092769
B46: 18-05-2025 | C46: 88.55 | D46: =(C46/C45)-1 -> 0.031450204 | F46: 24853.15 | G46: =(F46/F45)-1 -> 0.0041392769
B47: 45966 | C47: 101.33 | D47: =(C47/C46)-1 -> 0.14432524 | F47: 25019.8 | G47: =(F47/F46)-1 -> 0.0067053874
B48: 45752 | C48: 92.52 | D48: =(C48/C47)-1 -> -0.086943649 | F48: 24008 | G48: =(F48/F47)-1 -> -0.040439972
B49: 27-04-2025 | C49: 93.35 | D49: =(C49/C48)-1 -> 0.0089710333 | F49: 24346.7 | G49: =(F49/F48)-1 -> 0.014107797
B50: 20-04-2025 | C50: 96.25 | D50: =(C50/C49)-1 -> 0.031065881 | F50: 24039.35 | G50: =(F50/F49)-1 -> -0.012623887
B51: 13-04-2025 | C51: 97 | D51: =(C51/C50)-1 -> 0.0077922078 | F51: 23851.65 | G51: =(F51/F50)-1 -> -0.0078080314
B52: 45812 | C52: 92.55 | D52: =(C52/C51)-1 -> -0.045876289 | F52: 22828.55 | G52: =(F52/F51)-1 -> -0.042894307
B53: 30-03-2025 | C53: 94.12 | D53: =(C53/C52)-1 -> 0.016963803 | F53: 22904.45 | G53: =(F53/F52)-1 -> 0.0033247841
B54: 23-03-2025 | C54: 93.38 | D54: =(C54/C53)-1 -> -0.0078623034 | F54: 23519.35 | G54: =(F54/F53)-1 -> 0.026846312
B55: 16-03-2025 | C55: 92.28 | D55: =(C55/C54)-1 -> -0.011779824 | F55: 23350.4 | G55: =(F55/F54)-1 -> -0.0071834468
B56: 45903 | C56: 87.47 | D56: =(C56/C55)-1 -> -0.052123971 | F56: 22397.2 | G56: =(F56/F55)-1 -> -0.040821571
B57: 45691 | C57: 88.29 | D57: =(C57/C56)-1 -> 0.0093746427 | F57: 22552.5 | G57: =(F57/F56)-1 -> 0.0069339025
B58: 23-02-2025 | C58: 88.23 | D58: =(C58/C57)-1 -> -0.00067957866 | F58: 22124.7 | G58: =(F58/F57)-1 -> -0.018969072
B59: 16-02-2025 | C59: 91.31 | D59: =(C59/C58)-1 -> 0.034908761 | F59: 22795.9 | G59: =(F59/F58)-1 -> 0.030337135
B60: 45902 | C60: 90.22 | D60: =(C60/C59)-1 -> -0.011937356 | F60: 22929.25 | G60: =(F60/F59)-1 -> 0.0058497361
B61: 45690 | C61: 100.42 | D61: =(C61/C60)-1 -> 0.11305697 | F61: 23559.95 | G61: =(F61/F60)-1 -> 0.027506351
B62: 26-01-2025 | C62: 99.79 | D62: =(C62/C61)-1 -> -0.0062736507 | F62: 23508.4 | G62: =(F62/F61)-1 -> -0.0021880352
B63: 19-01-2025 | C63: 99.07 | D63: =(C63/C62)-1 -> -0.0072151518 | F63: 23092.2 | G63: =(F63/F62)-1 -> -0.01770431
B64: 45992 | C64: 100.1 | D64: =(C64/C63)-1 -> 0.010396689 | F64: 23203.2 | G64: =(F64/F63)-1 -> 0.0048068179
B65: 45778 | C65: 99.88 | D65: =(C65/C64)-1 -> -0.0021978022 | F65: 23431.5 | G65: =(F65/F64)-1 -> 0.0098391601
B66: 29-12-2024 | C66: 102.3 | D66: =(C66/C65)-1 -> 0.024229075 | F66: 24004.75 | G66: =(F66/F65)-1 -> 0.02446493
B67: 22-12-2024 | C67: 102.76 | D67: =(C67/C66)-1 -> 0.0044965787 | F67: 23813.4 | G67: =(F67/F66)-1 -> -0.007971339
B68: 15-12-2024 | C68: 102.83 | D68: =(C68/C67)-1 -> 0.00068119891 | F68: 23587.5 | G68: =(F68/F67)-1 -> -0.0094862556
B69: 45516 | C69: 109.81 | D69: =(C69/C68)-1 -> 0.067879024 | F69: 24768.3 | G69: =(F69/F68)-1 -> 0.050060413
B70: 45303 | C70: 111.94 | D70: =(C70/C69)-1 -> 0.019397141 | F70: 24677.8 | G70: =(F70/F69)-1 -> -0.003653864
B71: 24-11-2024 | C71: 114.32 | D71: =(C71/C70)-1 -> 0.02126139 | F71: 24131.1 | G71: =(F71/F70)-1 -> -0.022153514
B72: 17-11-2024 | C72: 105.14 | D72: =(C72/C71)-1 -> -0.08030091 | F72: 23907.25 | G72: =(F72/F71)-1 -> -0.0092764109
B73: 45576 | C73: 105.2 | D73: =(C73/C72)-1 -> 0.00057066768 | F73: 23532.7 | G73: =(F73/F72)-1 -> -0.015666796
B74: 45362 | C74: 108.28 | D74: =(C74/C73)-1 -> 0.029277567 | F74: 24148.2 | G74: =(F74/F73)-1 -> 0.026155095
B75: 27-10-2024 | C75: 114.43 | D75: =(C75/C74)-1 -> 0.056797192 | F75: 24304.35 | G75: =(F75/F74)-1 -> 0.0064663205
B76: 20-10-2024 | C76: 109.42 | D76: =(C76/C75)-1 -> -0.043782225 | F76: 24180.8 | G76: =(F76/F75)-1 -> -0.0050834521
B77: 13-10-2024 | C77: 121.72 | D77: =(C77/C76)-1 -> 0.11241089 | F77: 24854.05 | G77: =(F77/F76)-1 -> 0.027842338
B78: 45453 | C78: 123.98 | D78: =(C78/C77)-1 -> 0.018567203 | F78: 24964.25 | G78: =(F78/F77)-1 -> 0.004433885
B79: 29-09-2024 | C79: 121.34 | D79: =(C79/C78)-1 -> -0.021293757 | F79: 25014.6 | G79: =(F79/F78)-1 -> 0.0020168841
B80: 22-09-2024 | C80: 128.3 | D80: =(C80/C79)-1 -> 0.057359486 | F80: 26178.95 | G80: =(F80/F79)-1 -> 0.046546817
B81: 15-09-2024 | C81: 119.43 | D81: =(C81/C80)-1 -> -0.06913484 | F81: 25790.95 | G81: =(F81/F80)-1 -> -0.014821068
B82: 45513 | C82: 119.72 | D82: =(C82/C81)-1 -> 0.0024282006 | F82: 25356.5 | G82: =(F82/F81)-1 -> -0.016845056
B83: 45300 | C83: 112.65 | D83: =(C83/C82)-1 -> -0.05905446 | F83: 24852.15 | G83: =(F83/F82)-1 -> -0.019890363
B84: 25-08-2024 | C84: 113.58 | D84: =(C84/C83)-1 -> 0.0082556591 | F84: 25235.9 | G84: =(F84/F83)-1 -> 0.01544132
B85: 18-08-2024 | C85: 116.42 | D85: =(C85/C84)-1 -> 0.025004402 | F85: 24823.15 | G85: =(F85/F84)-1 -> -0.016355668
B86: 45604 | C86: 116.4 | D86: =(C86/C85)-1 -> -0.00017179179 | F86: 24541.15 | G86: =(F86/F85)-1 -> -0.011360363
B87: 45390 | C87: 118.31 | D87: =(C87/C86)-1 -> 0.016408935 | F87: 24367.5 | G87: =(F87/F86)-1 -> -0.0070758705
B88: 28-07-2024 | C88: 122.25 | D88: =(C88/C87)-1 -> 0.033302341 | F88: 24717.7 | G88: =(F88/F87)-1 -> 0.014371602
B89: 21-07-2024 | C89: 120.25 | D89: =(C89/C88)-1 -> -0.016359918 | F89: 24834.85 | G89: =(F89/F88)-1 -> 0.0047395186
B90: 14-07-2024 | C90: 115 | D90: =(C90/C89)-1 -> -0.043659044 | F90: 24530.9 | G90: =(F90/F89)-1 -> -0.01223885
B91: 45480 | C91: 117.77 | D91: =(C91/C90)-1 -> 0.024086957 | F91: 24502.15 | G91: =(F91/F90)-1 -> -0.0011719912
B92: 30-06-2024 | C92: 119.39 | D92: =(C92/C91)-1 -> 0.013755625 | F92: 24323.85 | G92: =(F92/F91)-1 -> -0.0072769124
B93: 23-06-2024 | C93: 113.74 | D93: =(C93/C92)-1 -> -0.047323896 | F93: 24010.6 | G93: =(F93/F92)-1 -> -0.012878307
B94: 16-06-2024 | C94: 114.74 | D94: =(C94/C93)-1 -> 0.0087919817 | F94: 23501.1 | G94: =(F94/F93)-1 -> -0.021219795
B95: 45541 | C95: 119.74 | D95: =(C95/C94)-1 -> 0.043576782 | F95: 23465.6 | G95: =(F95/F94)-1 -> -0.0015105676
B96: 45328 | C96: 118.13 | D96: =(C96/C95)-1 -> -0.013445799 | F96: 23290.15 | G96: =(F96/F95)-1 -> -0.0074769024
B97: 26-05-2024 | C97: 104.81 | D97: =(C97/C96)-1 -> -0.11275713 | F97: 22530.7 | G97: =(F97/F96)-1 -> -0.032608206
B98: 19-05-2024 | C98: 105.69 | D98: =(C98/C97)-1 -> 0.0083961454 | F98: 22957.1 | G98: =(F98/F97)-1 -> 0.018925289
B99: 45631 | C99: 96.56 | D99: =(C99/C98)-1 -> -0.08638471 | F99: 22466.1 | G99: =(F99/F98)-1 -> -0.021387719
B100: 45417 | C100: 93.59 | D100: =(C100/C99)-1 -> -0.030758078 | F100: 22055.2 | G100: =(F100/F99)-1 -> -0.018289779
B101: 28-04-2024 | C101: 92.61 | D101: =(C101/C100)-1 -> -0.010471204 | F101: 22475.85 | G101: =(F101/F100)-1 -> 0.0190726
B102: 21-04-2024 | C102: 97.85 | D102: =(C102/C101)-1 -> 0.056581363 | F102: 22419.95 | G102: =(F102/F101)-1 -> -0.0024871139
B103: 14-04-2024 | C103: 84.37 | D103: =(C103/C102)-1 -> -0.13776188 | F103: 22147 | G103: =(F103/F102)-1 -> -0.012174425
B104: 45477 | C104: 85.25 | D104: =(C104/C103)-1 -> 0.010430248 | F104: 22519.4 | G104: =(F104/F103)-1 -> 0.016814918
B105: 31-03-2024 | C105: 86.49 | D105: =(C105/C104)-1 -> 0.014545455 | F105: 22513.7 | G105: =(F105/F104)-1 -> -0.00025311509
B106: 24-03-2024 | C106: 74.9 | D106: =(C106/C105)-1 -> -0.13400393 | F106: 22326.9 | G106: =(F106/F105)-1 -> -0.0082971702
...

Sheet Manyavar- Beta Regression
B5: Regression Beta-2 Years weekly
B7: Avenue Supermarket Weekly Returns | F7: NIFTY Returns | I7: Beta Drifting
B9: Date | C9: Closing Price | D9: Return | F9: Closing Price | G9: Return | I9: Levered Raw Beta | J9: =M10 -> -0.19132287
B10: 25-01-2026 | C10: 475.2 | F10: 25320.65 | I10: Beta Weight | J10: 0.75 | L10: Beta 1 | M10: =SLOPE(D11:D113,G11:G113) -> -0.19132287
B11: 18-01-2026 | C11: 485.35 | D11: =(C11/C10)-1 -> 0.021359428 | F11: 25048.65 | G11: =(F11/F10)-1 -> -0.01074222 | L11: Beta 2 | M11: =_xlfn.COVARIANCE.S(D10:D113,G10:G113)/_xlfn.VAR.S(G10:G113) -> -0.19132287
B12: 46327 | C12: 484.5 | D12: =(C12/C11)-1 -> -0.0017513135 | F12: 25694.35 | G12: =(F12/F11)-1 -> 0.025777836 | I12: Market Beta | J12: 1
B13: 46113 | C13: 528.15 | D13: =(C13/C12)-1 -> 0.090092879 | F13: 25683.3 | G13: =(F13/F12)-1 -> -0.00043005563 | I13: Market Beta weight | J13: 0.25 | L13: Beta 3 | M13: =M32 -> -0.19132287
B14: 28-12-2025 | C14: 540.45 | D14: =(C14/C13)-1 -> 0.023288838 | F14: 26328.55 | G14: =(F14/F13)-1 -> 0.025123329
B15: 21-12-2025 | C15: 579.65 | D15: =(C15/C14)-1 -> 0.072532149 | F15: 26042.3 | G15: =(F15/F14)-1 -> -0.010872228 | I15: Adjusted Beta | J15: =(J9*J10)+(J12*J13) -> 0.10650785 | L15: SUMMARY OUTPUT
B16: 14-12-2025 | C16: 578.8 | D16: =(C16/C15)-1 -> -0.0014664021 | F16: 25966.4 | G16: =(F16/F15)-1 -> -0.0029144891
B17: 45850 | C17: 598.2 | D17: =(C17/C16)-1 -> 0.033517623 | F17: 26046.95 | G17: =(F17/F16)-1 -> 0.0031020858 | L17: Regression Statistics
B18: 30-11-2025 | C18: 596.35 | D18: =(C18/C17)-1 -> -0.0030926112 | F18: 26186.45 | G18: =(F18/F17)-1 -> 0.0053557134 | L18: Multiple R | M18: 0.076380859
B19: 23-11-2025 | C19: 597.25 | D19: =(C19/C18)-1 -> 0.0015091809 | F19: 26202.95 | G19: =(F19/F18)-1 -> 0.00063009686 | L19: R Square | M19: 0.0058340357
B20: 16-11-2025 | C20: 608.15 | D20: =(C20/C19)-1 -> 0.018250314 | F20: 26068.15 | G20: =(F20/F19)-1 -> -0.0051444589 | L20: Adjusted R Square | M20: -0.0040091917
B21: 45911 | C21: 608.15 | D21: =(C21/C20)-1 -> 0 | F21: 25910.05 | G21: =(F21/F20)-1 -> -0.0060648723 | L21: Standard Error | M21: 0.042271936
B22: 45699 | C22: 626.5 | D22: =(C22/C21)-1 -> 0.030173477 | F22: 25492.3 | G22: =(F22/F21)-1 -> -0.016123087 | L22: Observations | M22: 103
B23: 26-10-2025 | C23: 639.5 | D23: =(C23/C22)-1 -> 0.0207502 | F23: 25722.1 | G23: =(F23/F22)-1 -> 0.0090144867
B24: 19-10-2025 | C24: 645.75 | D24: =(C24/C23)-1 -> 0.0097732604 | F24: 25795.15 | G24: =(F24/F23)-1 -> 0.0028399703 | L24: ANOVA
B25: 46001 | C25: 688.2 | D25: =(C25/C24)-1 -> 0.065737515 | F25: 25709.85 | G25: =(F25/F24)-1 -> -0.0033068232 | M25: df | N25: SS | O25: MS | P25: F | Q25: Significance F
B26: 45787 | C26: 691.35 | D26: =(C26/C25)-1 -> 0.0045771578 | F26: 25285.35 | G26: =(F26/F25)-1 -> -0.016511182 | L26: Regression | M26: 1 | N26: 0.0010590973 | O26: 0.0010590973 | P26: 0.59269541 | Q26: 0.44317561
B27: 28-09-2025 | C27: 697.2 | D27: =(C27/C26)-1 -> 0.0084617054 | F27: 24894.25 | G27: =(F27/F26)-1 -> -0.015467454 | L27: Residual | M27: 101 | N27: 0.18047858 | O27: 0.0017869166
B28: 21-09-2025 | C28: 694.9 | D28: =(C28/C27)-1 -> -0.0032989099 | F28: 24654.7 | G28: =(F28/F27)-1 -> -0.009622704 | L28: Total | M28: 102 | N28: 0.18153768
B29: 14-09-2025 | C29: 704 | D29: =(C29/C28)-1 -> 0.013095409 | F29: 25327.05 | G29: =(F29/F28)-1 -> 0.027270662
B30: 45847 | C30: 717.55 | D30: =(C30/C29)-1 -> 0.019247159 | F30: 25114 | G30: =(F30/F29)-1 -> -0.0084119548 | M30: Coefficients | N30: Standard Error | O30: t Stat | P30: P-value | Q30: Lower 95% | R30: Upper 95% | S30: Lower 95.0% | T30: Upper 95.0%
B31: 31-08-2025 | C31: 723.05 | D31: =(C31/C30)-1 -> 0.0076649711 | F31: 24741 | G31: =(F31/F30)-1 -> -0.014852274 | L31: Intercept | M31: 0.0075782282 | N31: 0.0041780785 | O31: 1.8138071 | P31: 0.072676723 | Q31: -0.00070995555 | R31: 0.015866412 | S31: -0.00070995555 | T31: 0.015866412
B32: 24-08-2025 | C32: 724 | D32: =(C32/C31)-1 -> 0.0013138787 | F32: 24426.85 | G32: =(F32/F31)-1 -> -0.012697547 | L32: X Variable 1 | M32: -0.19132287 | N32: 0.24851414 | O32: -0.76986714 | P32: 0.44317561 | Q32: -0.68430807 | R32: 0.30166233 | S32: -0.68430807 | T32: 0.30166233
B33: 17-08-2025 | C33: 740.95 | D33: =(C33/C32)-1 -> 0.023411602 | F33: 24870.1 | G33: =(F33/F32)-1 -> 0.018146016
B34: 45938 | C34: 776.25 | D34: =(C34/C33)-1 -> 0.047641541 | F34: 24631.3 | G34: =(F34/F33)-1 -> -0.0096018914
B35: 45724 | C35: 743.6 | D35: =(C35/C34)-1 -> -0.042061192 | F35: 24363.3 | G35: =(F35/F34)-1 -> -0.010880465
B36: 27-07-2025 | C36: 741 | D36: =(C36/C35)-1 -> -0.0034965035 | F36: 24565.35 | G36: =(F36/F35)-1 -> 0.0082932115
B37: 20-07-2025 | C37: 742.45 | D37: =(C37/C36)-1 -> 0.0019568151 | F37: 24837 | G37: =(F37/F36)-1 -> 0.011058259
B38: 13-07-2025 | C38: 787.9 | D38: =(C38/C37)-1 -> 0.061216244 | F38: 24968.4 | G38: =(F38/F37)-1 -> 0.005290494
B39: 45815 | C39: 799.25 | D39: =(C39/C38)-1 -> 0.014405381 | F39: 25149.85 | G39: =(F39/F38)-1 -> 0.0072671857
B40: 29-06-2025 | C40: 796.1 | D40: =(C40/C39)-1 -> -0.0039411949 | F40: 25461 | G40: =(F40/F39)-1 -> 0.012371843
B41: 22-06-2025 | C41: 827.5 | D41: =(C41/C40)-1 -> 0.039442281 | F41: 25637.8 | G41: =(F41/F40)-1 -> 0.0069439535
B42: 15-06-2025 | C42: 804.05 | D42: =(C42/C41)-1 -> -0.028338369 | F42: 25112.4 | G42: =(F42/F41)-1 -> -0.020493178
B43: 45875 | C43: 800.7 | D43: =(C43/C42)-1 -> -0.0041664076 | F43: 24718.6 | G43: =(F43/F42)-1 -> -0.015681496
B44: 45663 | C44: 786.4 | D44: =(C44/C43)-1 -> -0.017859373 | F44: 25003.05 | G44: =(F44/F43)-1 -> 0.011507529
B45: 25-05-2025 | C45: 819.7 | D45: =(C45/C44)-1 -> 0.042344863 | F45: 24750.7 | G45: =(F45/F44)-1 -> -0.010092769
B46: 18-05-2025 | C46: 797.3 | D46: =(C46/C45)-1 -> -0.027327071 | F46: 24853.15 | G46: =(F46/F45)-1 -> 0.0041392769
B47: 45966 | C47: 734.5 | D47: =(C47/C46)-1 -> -0.078765835 | F47: 25019.8 | G47: =(F47/F46)-1 -> 0.0067053874
B48: 45752 | C48: 751.6 | D48: =(C48/C47)-1 -> 0.023281144 | F48: 24008 | G48: =(F48/F47)-1 -> -0.040439972
B49: 27-04-2025 | C49: 723.05 | D49: =(C49/C48)-1 -> -0.037985631 | F49: 24346.7 | G49: =(F49/F48)-1 -> 0.014107797
B50: 20-04-2025 | C50: 772.8 | D50: =(C50/C49)-1 -> 0.068805753 | F50: 24039.35 | G50: =(F50/F49)-1 -> -0.012623887
B51: 13-04-2025 | C51: 793.55 | D51: =(C51/C50)-1 -> 0.026850414 | F51: 23851.65 | G51: =(F51/F50)-1 -> -0.0078080314
B52: 45812 | C52: 777.9 | D52: =(C52/C51)-1 -> -0.019721505 | F52: 22828.55 | G52: =(F52/F51)-1 -> -0.042894307
B53: 30-03-2025 | C53: 802.45 | D53: =(C53/C52)-1 -> 0.031559326 | F53: 22904.45 | G53: =(F53/F52)-1 -> 0.0033247841
B54: 23-03-2025 | C54: 765.65 | D54: =(C54/C53)-1 -> -0.045859555 | F54: 23519.35 | G54: =(F54/F53)-1 -> 0.026846312
B55: 16-03-2025 | C55: 775.85 | D55: =(C55/C54)-1 -> 0.013322014 | F55: 23350.4 | G55: =(F55/F54)-1 -> -0.0071834468
B56: 45903 | C56: 780.6 | D56: =(C56/C55)-1 -> 0.0061223175 | F56: 22397.2 | G56: =(F56/F55)-1 -> -0.040821571
B57: 45691 | C57: 778.4 | D57: =(C57/C56)-1 -> -0.0028183449 | F57: 22552.5 | G57: =(F57/F56)-1 -> 0.0069339025
B58: 23-02-2025 | C58: 832.95 | D58: =(C58/C57)-1 -> 0.070079651 | F58: 22124.7 | G58: =(F58/F57)-1 -> -0.018969072
B59: 16-02-2025 | C59: 843.15 | D59: =(C59/C58)-1 -> 0.012245633 | F59: 22795.9 | G59: =(F59/F58)-1 -> 0.030337135
B60: 45902 | C60: 872.5 | D60: =(C60/C59)-1 -> 0.034809939 | F60: 22929.25 | G60: =(F60/F59)-1 -> 0.0058497361
B61: 45690 | C61: 880.05 | D61: =(C61/C60)-1 -> 0.0086532951 | F61: 23559.95 | G61: =(F61/F60)-1 -> 0.027506351
B62: 26-01-2025 | C62: 935.7 | D62: =(C62/C61)-1 -> 0.063235043 | F62: 23508.4 | G62: =(F62/F61)-1 -> -0.0021880352
B63: 19-01-2025 | C63: 933.8 | D63: =(C63/C62)-1 -> -0.0020305654 | F63: 23092.2 | G63: =(F63/F62)-1 -> -0.01770431
B64: 45992 | C64: 1132.6 | D64: =(C64/C63)-1 -> 0.21289355 | F64: 23203.2 | G64: =(F64/F63)-1 -> 0.0048068179
B65: 45778 | C65: 1194.2 | D65: =(C65/C64)-1 -> 0.054388133 | F65: 23431.5 | G65: =(F65/F64)-1 -> 0.0098391601
B66: 29-12-2024 | C66: 1180.7 | D66: =(C66/C65)-1 -> -0.011304639 | F66: 24004.75 | G66: =(F66/F65)-1 -> 0.02446493
B67: 22-12-2024 | C67: 1257.45 | D67: =(C67/C66)-1 -> 0.065003811 | F67: 23813.4 | G67: =(F67/F66)-1 -> -0.007971339
B68: 15-12-2024 | C68: 1250.35 | D68: =(C68/C67)-1 -> -0.0056463478 | F68: 23587.5 | G68: =(F68/F67)-1 -> -0.0094862556
B69: 45516 | C69: 1299.05 | D69: =(C69/C68)-1 -> 0.038949094 | F69: 24768.3 | G69: =(F69/F68)-1 -> 0.050060413
B70: 45303 | C70: 1356.8 | D70: =(C70/C69)-1 -> 0.044455564 | F70: 24677.8 | G70: =(F70/F69)-1 -> -0.003653864
B71: 24-11-2024 | C71: 1339.35 | D71: =(C71/C70)-1 -> -0.012861144 | F71: 24131.1 | G71: =(F71/F70)-1 -> -0.022153514
B72: 17-11-2024 | C72: 1434.2 | D72: =(C72/C71)-1 -> 0.070817934 | F72: 23907.25 | G72: =(F72/F71)-1 -> -0.0092764109
B73: 45576 | C73: 1388.55 | D73: =(C73/C72)-1 -> -0.031829591 | F73: 23532.7 | G73: =(F73/F72)-1 -> -0.015666796
B74: 45362 | C74: 1321.35 | D74: =(C74/C73)-1 -> -0.048395809 | F74: 24148.2 | G74: =(F74/F73)-1 -> 0.026155095
B75: 27-10-2024 | C75: 1400.5 | D75: =(C75/C74)-1 -> 0.059900859 | F75: 24304.35 | G75: =(F75/F74)-1 -> 0.0064663205
B76: 20-10-2024 | C76: 1395.3 | D76: =(C76/C75)-1 -> -0.0037129597 | F76: 24180.8 | G76: =(F76/F75)-1 -> -0.0050834521
B77: 13-10-2024 | C77: 1269.35 | D77: =(C77/C76)-1 -> -0.090267326 | F77: 24854.05 | G77: =(F77/F76)-1 -> 0.027842338
B78: 45453 | C78: 1325.35 | D78: =(C78/C77)-1 -> 0.044117068 | F78: 24964.25 | G78: =(F78/F77)-1 -> 0.004433885
B79: 29-09-2024 | C79: 1320.05 | D79: =(C79/C78)-1 -> -0.0039989437 | F79: 25014.6 | G79: =(F79/F78)-1 -> 0.0020168841
B80: 22-09-2024 | C80: 1298.9 | D80: =(C80/C79)-1 -> -0.01602212 | F80: 26178.95 | G80: =(F80/F79)-1 -> 0.046546817
B81: 15-09-2024 | C81: 1350.7 | D81: =(C81/C80)-1 -> 0.039879898 | F81: 25790.95 | G81: =(F81/F80)-1 -> -0.014821068
B82: 45513 | C82: 1292.3 | D82: =(C82/C81)-1 -> -0.04323684 | F82: 25356.5 | G82: =(F82/F81)-1 -> -0.016845056
B83: 45300 | C83: 1286.8 | D83: =(C83/C82)-1 -> -0.0042559777 | F83: 24852.15 | G83: =(F83/F82)-1 -> -0.019890363
B84: 25-08-2024 | C84: 1249.25 | D84: =(C84/C83)-1 -> -0.029180914 | F84: 25235.9 | G84: =(F84/F83)-1 -> 0.01544132
B85: 18-08-2024 | C85: 1250.4 | D85: =(C85/C84)-1 -> 0.00092055233 | F85: 24823.15 | G85: =(F85/F84)-1 -> -0.016355668
B86: 45604 | C86: 1174.25 | D86: =(C86/C85)-1 -> -0.060900512 | F86: 24541.15 | G86: =(F86/F85)-1 -> -0.011360363
B87: 45390 | C87: 1121.5 | D87: =(C87/C86)-1 -> -0.044922291 | F87: 24367.5 | G87: =(F87/F86)-1 -> -0.0070758705
B88: 28-07-2024 | C88: 1121.4 | D88: =(C88/C87)-1 -> -8.9166295e-05 | F88: 24717.7 | G88: =(F88/F87)-1 -> 0.014371602
B89: 21-07-2024 | C89: 1138.25 | D89: =(C89/C88)-1 -> 0.015025861 | F89: 24834.85 | G89: =(F89/F88)-1 -> 0.0047395186
B90: 14-07-2024 | C90: 1082.8 | D90: =(C90/C89)-1 -> -0.048715133 | F90: 24530.9 | G90: =(F90/F89)-1 -> -0.01223885
B91: 45480 | C91: 1036.3 | D91: =(C91/C90)-1 -> -0.042944219 | F91: 24502.15 | G91: =(F91/F90)-1 -> -0.0011719912
B92: 30-06-2024 | C92: 1026.1 | D92: =(C92/C91)-1 -> -0.0098427096 | F92: 24323.85 | G92: =(F92/F91)-1 -> -0.0072769124
B93: 23-06-2024 | C93: 1094.65 | D93: =(C93/C92)-1 -> 0.066806354 | F93: 24010.6 | G93: =(F93/F92)-1 -> -0.012878307
B94: 16-06-2024 | C94: 1051.65 | D94: =(C94/C93)-1 -> -0.039281962 | F94: 23501.1 | G94: =(F94/F93)-1 -> -0.021219795
B95: 45541 | C95: 1120.15 | D95: =(C95/C94)-1 -> 0.065135739 | F95: 23465.6 | G95: =(F95/F94)-1 -> -0.0015105676
B96: 45328 | C96: 1147.65 | D96: =(C96/C95)-1 -> 0.024550283 | F96: 23290.15 | G96: =(F96/F95)-1 -> -0.0074769024
B97: 26-05-2024 | C97: 1114.5 | D97: =(C97/C96)-1 -> -0.028885113 | F97: 22530.7 | G97: =(F97/F96)-1 -> -0.032608206
B98: 19-05-2024 | C98: 1043.25 | D98: =(C98/C97)-1 -> -0.063930013 | F98: 22957.1 | G98: =(F98/F97)-1 -> 0.018925289
B99: 45631 | C99: 1023.2 | D99: =(C99/C98)-1 -> -0.019218787 | F99: 22466.1 | G99: =(F99/F98)-1 -> -0.021387719
B100: 45417 | C100: 1044 | D100: =(C100/C99)-1 -> 0.020328382 | F100: 22055.2 | G100: =(F100/F99)-1 -> -0.018289779
B101: 28-04-2024 | C101: 983.55 | D101: =(C101/C100)-1 -> -0.057902299 | F101: 22475.85 | G101: =(F101/F100)-1 -> 0.0190726
B102: 21-04-2024 | C102: 932.6 | D102: =(C102/C101)-1 -> -0.051802145 | F102: 22419.95 | G102: =(F102/F101)-1 -> -0.0024871139
B103: 14-04-2024 | C103: 937.55 | D103: =(C103/C102)-1 -> 0.0053077418 | F103: 22147 | G103: =(F103/F102)-1 -> -0.012174425
B104: 45477 | C104: 918.3 | D104: =(C104/C103)-1 -> -0.020532238 | F104: 22519.4 | G104: =(F104/F103)-1 -> 0.016814918
B105: 31-03-2024 | C105: 914.35 | D105: =(C105/C104)-1 -> -0.0043014265 | F105: 22513.7 | G105: =(F105/F104)-1 -> -0.00025311509
B106: 24-03-2024 | C106: 909.65 | D106: =(C106/C105)-1 -> -0.0051402636 | F106: 22326.9 | G106: =(F106/F105)-1 -> -0.0082971702
...
